{
  "entity": "MediaReport",
  "title": "获取开源情报的数据列表 Swagger",
  "spec": "data__swagger__开源情报的列表接口.json",
  "source": "https://ontology.example.test (redacted)",
  "http_status": 200,
  "resultCode": 200,
  "message": null,
  "recordTotal": 76,
  "columnNames": [
    "id",
    "name",
    "catCode",
    "sourceOrigin",
    "curStatus",
    "typeCode",
    "subordinateTo",
    "influenceType",
    "eventTrend",
    "sourceUrl",
    "contentSummary",
    "publishTime",
    "sourcePlatform",
    "credibilityScore",
    "keywordTags",
    "relatedEvent",
    "socialAccount",
    "publisher",
    "imageUrl",
    "relatedPlatform",
    "confidentialityLevel",
    "rawDataBlockPtr",
    "reliability",
    "refCollectionTask",
    "startTime",
    "creatorId",
    "isSimulationData",
    "updateSeqnr",
    "dataUpdateTime"
  ],
  "columnDisplayNames": [
    "主键",
    "显示名",
    "类型编码",
    "数据原始出处",
    "当前状态",
    "类型",
    "隶属",
    "影响类型",
    "事件态势影响",
    "详情链接",
    "内容摘要\t",
    "发布时间",
    "来源平台",
    "可信度评分",
    "关键词标签",
    "关联事件",
    "来源社交账号",
    "发表者",
    "图片地址",
    "关联作战平台",
    "密级",
    "原始数据块存储句柄",
    "置信度（百分比）",
    "关联采集任务",
    "采集时间",
    "创建人编码",
    "是否仿真模拟数据",
    "更新序列号",
    "数据最后更新时间"
  ],
  "fetch_mode": "full",
  "rows_fetched": 76,
  "columns_in_rows": [
    "id",
    "name",
    "catCode",
    "sourceOrigin",
    "curStatus",
    "typeCode",
    "subordinateTo",
    "influenceType",
    "eventTrend",
    "sourceUrl",
    "contentSummary",
    "publishTime",
    "sourcePlatform",
    "credibilityScore",
    "keywordTags",
    "relatedEvent",
    "socialAccount",
    "publisher",
    "imageUrl",
    "relatedPlatform",
    "confidentialityLevel",
    "rawDataBlockPtr",
    "reliability",
    "refCollectionTask",
    "startTime",
    "creatorId",
    "isSimulationData",
    "updateSeqnr",
    "dataUpdateTime"
  ],
  "rows": [
    {
      "rawDataBlockPtr": null,
      "relatedPlatform": "CVN-T08",
      "reliability": "中高",
      "creatorId": null,
      "curStatus": null,
      "confidentialityLevel": null,
      "sourceUrl": "",
      "influenceType": null,
      "sourceOrigin": null,
      "credibilityScore": null,
      "imageUrl": null,
      "sourcePlatform": "OSINT_CARRIER_ACTIVITY_2020_2026",
      "startTime": "2026-06-15",
      "id": "00000000-0000-4000-8000-000000000000",
      "refCollectionTask": null,
      "dataUpdateTime": "2026-06-15T00:00",
      "contentSummary": "时间段 ① 2022/7/13 本年首次在测试海区丁行动。 ② 2022/7/22–7/26 测试港城乙访，7/28 返回测试海区丁（测试海峡甲局势升温背景）。 ③ 2022/8/3–8/20 测试海区丁活动（测试来源甲口径）。 ④ 2022/9/5–9/10 测试港城甲港访（测试来源甲口径）。 ⑤ 2022/10/15–10/18 马尼拉港访（GPT 口径）。；活动 ① 例行海上安全、飞行行动；② 环测试海区甲演习 RIMPAC 后半程、美韩联合反潜演练；③ 港口访问交流（近五年首次测试舰艇064航母访韩）；④ 同期属舰本福德 DDG-T60 在西沙/岛礁附近实施 FONOP。；停靠 ：①测试港城乙（7/22–7/26）；②韩国测试港城甲（9/5–9/10， USS 测试舰 访镇海）；③测试母港F（8/25–8/29）；④马尼拉（10/15–10/18）。；天气 ：无逐次公开数据；测试港城乙 7 月炎热潮湿短时雷阵雨；测试海区丁 8 月台风季外围云雨；测试港城甲 9 月初秋温和湿润。；补给 ：无逐次公开合同；2022/7 测试港城乙访/返测试海区丁期间公开出现 USNS 测试舰 航迹线索（媒体引用，未确认完整补给计划）。；参演 1）人员：测试舰CN05 CSG、 USS 测试舰 等护航舰人员。 2）船、飞机：测试舰CN05 CSG（CVW-T）；护航含安提坦 CG-T08、钱斯勒斯维尔 CG-T02；同期本福德 DDG-T60（FONOP）。 参演国家：测试舰艇064、测试港城乙、韩国、日本、加拿大（RIMPAC 相关）。；护航编成表 1）舰船表：①安提坦 CG-T08（巡洋舰）；②钱斯勒斯维尔 CG-T02（巡洋舰，2023 更名罗伯特·斯莫斯）；③本福德 DDG-T60；④测试水面舰038 DDG-T21（DESRON-15）。 2）飞机表：①第5舰载机联队（CVW-T）。",
      "publishTime": "2022-07-13T00:00",
      "relatedEvent": null,
      "socialAccount": null,
      "typeCode": null,
      "catCode": "MediaReport",
      "eventTrend": null,
      "isSimulationData": null,
      "subordinateTo": null,
      "updateSeqnr": null,
      "name": "CVN-T08 测试航母07：2022/7–2022/9 测试海区丁/测试海区戊部署（含测试港城甲首访）",
      "publisher": null,
      "keywordTags": "CVN-T08,测试航母07,测试舰艇064航母,测试海区丁,西测试海区甲,印太部署,2020-2026,OSINT"
    },
    {
      "rawDataBlockPtr": null,
      "relatedPlatform": "CVN-T09",
      "reliability": "中",
      "creatorId": null,
      "curStatus": null,
      "confidentialityLevel": null,
      "sourceUrl": "",
      "influenceType": null,
      "sourceOrigin": null,
      "credibilityScore": null,
      "imageUrl": null,
      "sourcePlatform": "OSINT_CARRIER_ACTIVITY_2020_2026",
      "startTime": "2026-06-15",
      "id": "00000000-0000-4000-8000-000000000000",
      "refCollectionTask": null,
      "dataUpdateTime": "2026-06-26T00:00",
      "contentSummary": "时间段 ① 2021/2/2 进入测试海区丁区域活动（测试来源甲口径 2/2–2/12）。 ② 2021/2/9 与测试水面舰065双航母合练（年度首次双航母测试海区丁演习）。；活动 ① 双航母协同演练、反潜/对海实装科目训练（2001 年以来印太少数双航母行动之一）。；停靠 ：无靠岸，全程海上机动补给。；天气 ：无逐次公开数据；测试海区丁北部 2 月东北季风期、阴天、东北大风 4–5 级。；补给 ：无逐次公开合同；MSC 远洋机动补给，海上对接 T-AO 补给船。；参演 1）人员：第11打击群指挥官 ⚠️存疑\"凯文·怀特少将\"（仅测试来源甲，英文主流未确认）。 2）船、飞机：测试舰CN01 CSG + 测试舰CN09 CSG；舰载机联队。 参演国家：测试舰艇064为主，日本（远程舰机协同）。；护航编成表 1）舰船表：①测试舰CN20 CG-T01（巡洋舰）；②拉塞尔 DDG-T38；③测试水面舰026 DDG-T61 等测试舰CN23级（事件1.md 口径，双航母编队）。 2）飞机表：①舰载机联队（CVW，番号未系统披露）。",
      "publishTime": "2021-02-02T00:00",
      "relatedEvent": null,
      "socialAccount": null,
      "typeCode": null,
      "catCode": "MediaReport",
      "eventTrend": null,
      "isSimulationData": null,
      "subordinateTo": null,
      "updateSeqnr": null,
      "name": "CVN-T09 测试航母03：2021 年 2 月 测试海区丁双航母行动（与测试水面舰065）",
      "publisher": null,
      "keywordTags": "CVN-T09,测试航母03,测试舰艇064航母,测试海区丁,西测试海区甲,印太部署,2020-2026,OSINT"
    },
    {
      "rawDataBlockPtr": null,
      "relatedPlatform": "CVN-T02",
      "reliability": "中高",
      "creatorId": null,
      "curStatus": null,
      "confidentialityLevel": null,
      "sourceUrl": "",
      "influenceType": null,
      "sourceOrigin": null,
      "credibilityScore": null,
      "imageUrl": null,
      "sourcePlatform": "OSINT_CARRIER_ACTIVITY_2020_2026",
      "startTime": "2026-06-15",
      "id": "00000000-0000-4000-8000-000000000000",
      "refCollectionTask": null,
      "dataUpdateTime": "2026-06-15T00:00",
      "contentSummary": "时间段 ：① 2024/8/13–8/15 进入测试海区丁。；活动 ：① 飞行作业与海上安全行动（短时存在展示，事件1.md 口径）。；停靠 ：未披露。；天气 ：无逐次公开数据；测试海区丁 8 月台风季、湿热多雷暴。；补给 ：无逐次公开合同。；参演 1）人员：CSG-T02、CVW-T 人员。 2）船、飞机：测试舰CN37 CSG（CVW-T）。 参演国家：测试舰艇064。；护航编成表 1）舰船表：①公开有限（DESRON-21 属舰）。 2）飞机表：①第9舰载机联队（CVW-T）。",
      "publishTime": "2024-08-13T00:00",
      "relatedEvent": null,
      "socialAccount": null,
      "typeCode": null,
      "catCode": "MediaReport",
      "eventTrend": null,
      "isSimulationData": null,
      "subordinateTo": null,
      "updateSeqnr": null,
      "name": "CVN-T02 测试航母12：2024/8 测试海区丁行动（CSG-T02 / CVW-T）",
      "publisher": null,
      "keywordTags": "CVN-T02,测试航母12,测试舰艇064航母,测试海区丁,西测试海区甲,印太部署,2020-2026,OSINT"
    },
    {
      "rawDataBlockPtr": null,
      "relatedPlatform": "CVN-T08",
      "reliability": "中高",
      "creatorId": null,
      "curStatus": null,
      "confidentialityLevel": null,
      "sourceUrl": "",
      "influenceType": null,
      "sourceOrigin": null,
      "credibilityScore": null,
      "imageUrl": null,
      "sourcePlatform": "OSINT_CARRIER_ACTIVITY_2020_2026",
      "startTime": "2026-06-15",
      "id": "00000000-0000-4000-8000-000000000000",
      "refCollectionTask": null,
      "dataUpdateTime": "2026-06-21T00:00",
      "contentSummary": "时间段 ① 2023/6/19–7/4 前后 测试海区丁行动；6/25 起岘港港访，港访后返回测试海区丁。 ② 2023/7 下旬 护身军刀 2023（Talisman Sabre，澳大利亚海域/测试海区丙边缘）。 ③ 2023/8/10–11/20 西太部署，9/5–9/22 测试海区丁（测试来源甲口径）。 ④ 2023/10/10–10/13 前后 美日韩三边演习后访问测试港城甲。 ⑤ 2023/10/28–11 上旬 马尼拉港访。；活动 ① 测试海区丁行动+越南岘港罕见航母港访（外交交流、休整）；② 护身军刀 2023 支援与澳海军交流；③ 美日法测试海区甲斯特勒、美韩黄海联合演练、测试海区丁常态化战备；④ 美日韩三边海上演习后测试港城甲港访；⑤ 菲律宾港访（测试海区丁争端升温背景下存在展示）。；停靠 ：①越南岘港/仙沙港 Tien Sa（2023/6/25 起，⚠️测试来源甲误记 10/3–10/7，以 6 月为准）；②韩国测试港城甲（10/12–10/13）；③菲律宾马尼拉（10/28 起）；④⚠️测试来源甲另记测试母港A 11/15–11/20。；天气 ：无逐次公开数据；岘港 6 月炎热潮湿、午后雷雨；测试港城甲 10 月秋季较凉爽干燥；马尼拉 10–11 月雨季末湿热。；补给 ：无逐次公开合同；港访含后勤、休整、交流。；参演 1）人员： 测试舰EN70 测试员147 Capt. Daryle Cardone （2023/10 测试港城甲公开露面）；美越接待与外交人员。 2）船、飞机：测试舰CN05 CSG（CVW-T）；护航含 USS 测试舰 (CG-T08)、 USS 测试舰 (CG-T02)。 参演国家：测试舰艇064、越南（港口交流）、澳大利亚（护身军刀）、日本、法国、韩国。；护航编成表 1）舰船表：①安提坦 CG-T08（巡洋舰）；②罗伯特·斯莫斯 CG-T02（原钱斯勒斯维尔，巡洋舰）；③DESRON-15 属舰。 2）飞机表：①第5舰载机联队（CVW-T）。",
      "publishTime": "2023-06-19T00:00",
      "relatedEvent": null,
      "socialAccount": null,
      "typeCode": null,
      "catCode": "MediaReport",
      "eventTrend": null,
      "isSimulationData": null,
      "subordinateTo": null,
      "updateSeqnr": null,
      "name": "CVN-T08 测试航母07：2023 越南岘港港访、护身军刀 2023 与测试港城甲/马尼拉",
      "publisher": null,
      "keywordTags": "CVN-T08,测试航母07,测试舰艇064航母,测试海区丁,西测试海区甲,印太部署,2020-2026,OSINT"
    },
    {
      "rawDataBlockPtr": null,
      "relatedPlatform": "CVN-T10",
      "reliability": "中高",
      "creatorId": null,
      "curStatus": null,
      "confidentialityLevel": null,
      "sourceUrl": null,
      "influenceType": null,
      "sourceOrigin": null,
      "credibilityScore": null,
      "imageUrl": "",
      "sourcePlatform": null,
      "startTime": "2026-06-15",
      "id": "00000000-0000-4000-8000-000000000000",
      "refCollectionTask": null,
      "dataUpdateTime": "2026-06-17T00:00",
      "contentSummary": "本地爱好者/观察账号于2026-05-10从测试母港A基地外拍摄CVN-T10离港海试画面。",
      "publishTime": "2026-05-10T00:00",
      "relatedEvent": null,
      "socialAccount": "source23",
      "typeCode": null,
      "catCode": "MediaReport",
      "eventTrend": null,
      "isSimulationData": null,
      "subordinateTo": null,
      "updateSeqnr": null,
      "name": "本地观察账号发布CVN-T10海试当天基地外实拍",
      "publisher": null,
      "keywordTags": "CVN-T10,USS 测试舰,测试水面舰044,测试母港A,测试海区己,测试母港F,2026年部署,OSINT,X,测试母港A,实景照片"
    },
    {
      "rawDataBlockPtr": null,
      "relatedPlatform": "CVN-T10",
      "reliability": "中高",
      "creatorId": null,
      "curStatus": null,
      "confidentialityLevel": null,
      "sourceUrl": null,
      "influenceType": null,
      "sourceOrigin": null,
      "credibilityScore": null,
      "imageUrl": "",
      "sourcePlatform": "AIS_TRACKER",
      "startTime": "2026-06-23",
      "id": "00000000-0000-4000-8000-000000000000",
      "refCollectionTask": null,
      "dataUpdateTime": "2026-06-22T00:00",
      "contentSummary": "AIS显示T-AO-207于2026-06-03 08:03至09:15抵达并进入测试母港F阿普拉港，强指向航母编队去向。",
      "publishTime": "2026-06-03T09:15",
      "relatedEvent": null,
      "socialAccount": null,
      "typeCode": null,
      "catCode": "MediaReport",
      "eventTrend": null,
      "isSimulationData": null,
      "subordinateTo": null,
      "updateSeqnr": null,
      "name": "T-AO-207抵达测试母港F阿普拉港末段AIS航迹",
      "publisher": null,
      "keywordTags": "CVN-T10,USS 测试舰,测试水面舰044,测试母港A,测试海区己,测试母港F,2026年部署,OSINT,AIS,T-AO-207,阿普拉港"
    },
    {
      "rawDataBlockPtr": null,
      "relatedPlatform": "CVN-T02",
      "reliability": "中",
      "creatorId": null,
      "curStatus": null,
      "confidentialityLevel": null,
      "sourceUrl": "",
      "influenceType": null,
      "sourceOrigin": null,
      "credibilityScore": null,
      "imageUrl": null,
      "sourcePlatform": "OSINT_CARRIER_ACTIVITY_2020_2026",
      "startTime": "2026-06-15",
      "id": "00000000-0000-4000-8000-000000000000",
      "refCollectionTask": null,
      "dataUpdateTime": "2026-06-16T00:00",
      "contentSummary": "时间段 ① 2022/1/3 部署启动（西太主力，测试来源甲记 1/3–8/6）。 ② 2022/1/18–22 测试海区己联合演训。 ③ 2022/1/23–24 与测试舰CN02双航母联合行动。 ④ 2022/3/23–25 测试海区丁行动后访问马尼拉湾。 ⑤ 2022/4/15–5/2 常驻测试海区丁（约 18 天）。 ⑥ 2022/4/18–23 与测试海区庚自联合行动（测试海区己/测试海区戊）。 ⑦ 2022/5 下旬 接替测试舰CN05号前沿轮换（佐世保）。；活动 ① \"护身军刀 2022\"预演、美菲\"肩并肩\"联合军演、自由航行、舰载机全天候起降训练；② 双航母多舰多机种协同（含大规模 F-35 运用，公开提及 26 架）；③ 2022/1/24 测试舰CN02一架 F-35C 着舰坠毁、7 人受伤 （同期双航母背景）；④ 与测试海区庚自舰载机展示与外交交流。；停靠 ：①马尼拉/马尼拉湾（3/25 起，测试来源甲记 4/28–5/1）；②测试母港F（6/10–6/15）；③日本测试母港A（7/20–7/26）。；天气 ：无逐次公开数据；4 月菲律宾周边热带低压多发、阵雨频繁；马尼拉 3 月炎热较干、午后局地雷雨。；补给 ：无逐次公开合同；⚠️测试来源甲记马尼拉油料由壳牌菲律宾、干货 OSC 海运（英文主流未确认承包商）。；参演 1）人员：⚠️存疑\"第3打击群指挥官弗雷德·戈尔德哈默少将\"（仅测试来源甲）；2022/4 测试舰艇064驻日大使 Rahm Emanuel 、日本外相 林芳正 登舰（公开）。 2）船、飞机：测试舰CN37 CSG（CVW-T）+ 测试舰CN02 CSG（双航母）；另与 USS 测试舰 在菲律宾周边活动。 参演国家：测试舰艇064、菲律宾、日本、澳大利亚、印度（马拉巴尔背景）。；护航编成表 1）舰船表：①测试舰CN15 CG-T12（巡洋舰）；②测试舰艇061 DDG-T44；③测试舰艇057 DDG-T13 等（DESRON-21）。 2）飞机表：①第9舰载机联队（CVW-T）。",
      "publishTime": "2022-01-03T00:00",
      "relatedEvent": null,
      "socialAccount": null,
      "typeCode": null,
      "catCode": "MediaReport",
      "eventTrend": null,
      "isSimulationData": null,
      "subordinateTo": null,
      "updateSeqnr": null,
      "name": "CVN-T02 测试航母12：2022/1–2022/8 西太主力部署（CSG-T02 / CVW-T）",
      "publisher": null,
      "keywordTags": "CVN-T02,测试航母12,测试舰艇064航母,测试海区丁,西测试海区甲,印太部署,2020-2026,OSINT"
    },
    {
      "rawDataBlockPtr": null,
      "relatedPlatform": "CVN-T10",
      "reliability": "中高",
      "creatorId": null,
      "curStatus": null,
      "confidentialityLevel": null,
      "sourceUrl": null,
      "influenceType": null,
      "sourceOrigin": null,
      "credibilityScore": null,
      "imageUrl": "",
      "sourcePlatform": "ADSB_TRACKER",
      "startTime": "2026-06-22",
      "id": "00000000-0000-4000-8000-000000000000",
      "refCollectionTask": null,
      "dataUpdateTime": "2026-06-19T00:00",
      "contentSummary": "2026-06-02 20时至2026-06-03 04时，ADS-B发现AA0003（H-60）在测试母港F以西活动，机型与CVW-T HSC-12/HSM-77吻合。",
      "publishTime": "2026-06-03T04:00",
      "relatedEvent": null,
      "socialAccount": null,
      "typeCode": null,
      "catCode": "MediaReport",
      "eventTrend": null,
      "isSimulationData": null,
      "subordinateTo": null,
      "updateSeqnr": null,
      "name": "ADS-B捕获AA0003 H-60出现在测试母港F以西",
      "publisher": null,
      "keywordTags": "CVN-T10,USS 测试舰,测试水面舰044,测试母港A,测试海区己,测试母港F,2026年部署,OSINT,ADS-B,AA0003,H-60,测试母港F以西"
    },
    {
      "rawDataBlockPtr": null,
      "relatedPlatform": "CVN-T08",
      "reliability": "中高",
      "creatorId": null,
      "curStatus": null,
      "confidentialityLevel": null,
      "sourceUrl": "",
      "influenceType": null,
      "sourceOrigin": null,
      "credibilityScore": null,
      "imageUrl": null,
      "sourcePlatform": "OSINT_CARRIER_ACTIVITY_2020_2026",
      "startTime": "2026-06-15",
      "id": "00000000-0000-4000-8000-000000000000",
      "refCollectionTask": null,
      "dataUpdateTime": "2026-06-13T00:00",
      "contentSummary": "时间段 ① 2020/7 月初—7 月中（7/6、7/17 两轮）。；活动 ：① 与测试航母03双航母高强度演习（2014 年以来首次两艘美航同时在测试海区丁）。；停靠 ：无公开港访记录。；天气 ：无逐次公开数据；测试海区丁 7 月西南季风/雨季。；补给 ：无逐次公开合同；MSC 海上横向补给。；参演 1）人员：CSG-T10 人员（普通名单不公开）。 2）船、飞机：测试舰CN05 CSG + 测试舰CN01 CSG；CVW-T。 参演国家：测试舰艇064。；护航编成表 1）舰船表：①公开有限。 2）飞机表：①第5舰载机联队（CVW-T）。",
      "publishTime": "2020-07-01T00:00",
      "relatedEvent": null,
      "socialAccount": null,
      "typeCode": null,
      "catCode": "MediaReport",
      "eventTrend": null,
      "isSimulationData": null,
      "subordinateTo": null,
      "updateSeqnr": null,
      "name": "CVN-T08 测试航母07：2020/7 测试海区丁双航母行动（与测试航母03）",
      "publisher": null,
      "keywordTags": "CVN-T08,测试航母07,测试舰艇064航母,测试海区丁,西测试海区甲,印太部署,2020-2026,OSINT"
    },
    {
      "rawDataBlockPtr": null,
      "relatedPlatform": null,
      "reliability": null,
      "creatorId": null,
      "curStatus": "PUBLISHED",
      "confidentialityLevel": null,
      "sourceUrl": "",
      "influenceType": "POSITIVE",
      "sourceOrigin": null,
      "credibilityScore": null,
      "imageUrl": null,
      "sourcePlatform": "SURFPAC",
      "startTime": null,
      "id": "OSINT_NICHOLAS_DELEO_002",
      "refCollectionTask": null,
      "dataUpdateTime": "2026-06-16T00:00",
      "contentSummary": "在接任测试舰艇064第七舰队旗舰蓝岭号测试员147仪式上发表讲话，强调与盟友及伙伴合作，维护自由开放的印太地区。",
      "publishTime": "2023-11-10T00:00",
      "relatedEvent": null,
      "socialAccount": null,
      "typeCode": null,
      "catCode": "MediaReport",
      "eventTrend": null,
      "isSimulationData": null,
      "subordinateTo": null,
      "updateSeqnr": null,
      "name": "就任蓝岭号测试员147发表讲话",
      "publisher": "source24",
      "keywordTags": "测试舰艇064海军,第七舰队,蓝岭号,印太地区,盟友合作"
    },
    {
      "rawDataBlockPtr": null,
      "relatedPlatform": null,
      "reliability": null,
      "creatorId": null,
      "curStatus": "PUBLISHED",
      "confidentialityLevel": null,
      "sourceUrl": "",
      "influenceType": "POSITIVE",
      "sourceOrigin": null,
      "credibilityScore": null,
      "imageUrl": null,
      "sourcePlatform": "LINKEDIN",
      "startTime": null,
      "id": "OSINT_NICHOLAS_DELEO_LI_001",
      "refCollectionTask": null,
      "dataUpdateTime": "2026-06-15T00:00",
      "contentSummary": "对测试舰艇064海军少将Dennis Velez退休公告发表评论：“Sir, the source06 is gonna miss you!!!!”，表达对其服役贡献的认可与敬意。",
      "publishTime": "2026-04-01T00:00",
      "relatedEvent": null,
      "socialAccount": "source25",
      "typeCode": null,
      "catCode": "MediaReport",
      "eventTrend": null,
      "isSimulationData": null,
      "subordinateTo": null,
      "updateSeqnr": null,
      "name": "评论海军少将丹尼斯·贝莱斯退休",
      "publisher": "source24",
      "keywordTags": "测试舰艇064海军,海军将领,退休,领导力,军官职业发展"
    },
    {
      "rawDataBlockPtr": null,
      "relatedPlatform": "CVN-T10",
      "reliability": "中高",
      "creatorId": null,
      "curStatus": null,
      "confidentialityLevel": null,
      "sourceUrl": null,
      "influenceType": null,
      "sourceOrigin": null,
      "credibilityScore": null,
      "imageUrl": "",
      "sourcePlatform": null,
      "startTime": "2026-06-23",
      "id": "00000000-0000-4000-8000-000000000000",
      "refCollectionTask": null,
      "dataUpdateTime": "2026-06-25T00:00",
      "contentSummary": "2026-05-30社媒发帖展示CVN-T10海上航行、舰载机甲板作业及ADS-B截图，标注AEEBA3/RUDY70与AE68AD/RUDY73两架CMV-22B。",
      "publishTime": "2026-05-30T00:00",
      "relatedEvent": null,
      "socialAccount": "[已脱敏-socialaccount]",
      "typeCode": null,
      "catCode": "MediaReport",
      "eventTrend": null,
      "isSimulationData": null,
      "subordinateTo": null,
      "updateSeqnr": null,
      "name": "社媒发布CVN-T10及随舰CMV-22B线索",
      "publisher": null,
      "keywordTags": "CVN-T10,USS 测试舰,测试水面舰044,测试母港A,测试海区己,测试母港F,2026年部署,OSINT,X,CMV-22B,RUDY70,RUDY73"
    },
    {
      "rawDataBlockPtr": null,
      "relatedPlatform": "CVN-T10",
      "reliability": "中高",
      "creatorId": null,
      "curStatus": null,
      "confidentialityLevel": null,
      "sourceUrl": null,
      "influenceType": null,
      "sourceOrigin": null,
      "credibilityScore": null,
      "imageUrl": "",
      "sourcePlatform": "JAPAN_MOFA",
      "startTime": "2026-06-16",
      "id": "00000000-0000-4000-8000-000000000000",
      "refCollectionTask": null,
      "dataUpdateTime": "2026-06-17T00:00",
      "contentSummary": "外务省/测试母港A公开通报显示CVN-T10原定2026-05-22 10:00左右离港，船员约5052人。",
      "publishTime": "2026-05-21T00:00",
      "relatedEvent": null,
      "socialAccount": null,
      "typeCode": null,
      "catCode": "MediaReport",
      "eventTrend": null,
      "isSimulationData": null,
      "subordinateTo": null,
      "updateSeqnr": null,
      "name": "日本公开通报CVN-T10原定6月21日出港",
      "publisher": null,
      "keywordTags": "CVN-T10,USS 测试舰,测试水面舰044,测试母港A,测试海区己,测试母港F,2026年部署,OSINT,日本通报,出港计划"
    },
    {
      "rawDataBlockPtr": null,
      "relatedPlatform": "CVN-T10",
      "reliability": "中高",
      "creatorId": null,
      "curStatus": null,
      "confidentialityLevel": null,
      "sourceUrl": "",
      "influenceType": null,
      "sourceOrigin": null,
      "credibilityScore": null,
      "imageUrl": "",
      "sourcePlatform": "STARS_AND_STRIPES",
      "startTime": "2026-06-15",
      "id": "00000000-0000-4000-8000-000000000000",
      "refCollectionTask": null,
      "dataUpdateTime": "2026-06-22T00:00",
      "contentSummary": "Stars and Stripes于2026-05-11报道测试水面舰044离开测试海区庚军基地开始年度部署。",
      "publishTime": "2026-05-11T00:00",
      "relatedEvent": null,
      "socialAccount": null,
      "typeCode": null,
      "catCode": "MediaReport",
      "eventTrend": null,
      "isSimulationData": null,
      "subordinateTo": null,
      "updateSeqnr": null,
      "name": "星条旗报道CVN-T10离开测试海区庚军基地开始年度部署",
      "publisher": null,
      "keywordTags": "CVN-T10,USS 测试舰,测试水面舰044,测试母港A,测试海区己,测试母港F,2026年部署,OSINT,Stars and Stripes,年度部署"
    },
    {
      "rawDataBlockPtr": null,
      "relatedPlatform": "CVN-T10",
      "reliability": "中高",
      "creatorId": null,
      "curStatus": null,
      "confidentialityLevel": null,
      "sourceUrl": null,
      "influenceType": null,
      "sourceOrigin": null,
      "credibilityScore": null,
      "imageUrl": "",
      "sourcePlatform": "TYPHOON_TRACKING",
      "startTime": "2026-06-15",
      "id": "00000000-0000-4000-8000-000000000000",
      "refCollectionTask": null,
      "dataUpdateTime": "2026-06-14T00:00",
      "contentSummary": "2026-06-01 02时台风“蔷薇”位于23.4N/127.5E并向北移动，阻断向日本方向折返，支持航母向测试海区己—测试母港F方向规避。",
      "publishTime": "2026-06-01T02:00",
      "relatedEvent": null,
      "socialAccount": null,
      "typeCode": null,
      "catCode": "MediaReport",
      "eventTrend": null,
      "isSimulationData": null,
      "subordinateTo": null,
      "updateSeqnr": null,
      "name": "2606号台风“蔷薇”路径图约束航母机动方向",
      "publisher": null,
      "keywordTags": "CVN-T10,USS 测试舰,测试水面舰044,测试母港A,测试海区己,测试母港F,2026年部署,OSINT,台风,气象约束,蔷薇"
    },
    {
      "rawDataBlockPtr": null,
      "relatedPlatform": "CVN-T10",
      "reliability": "中高",
      "creatorId": null,
      "curStatus": null,
      "confidentialityLevel": null,
      "sourceUrl": "",
      "influenceType": null,
      "sourceOrigin": null,
      "credibilityScore": null,
      "imageUrl": "",
      "sourcePlatform": "USINDOPACOM",
      "startTime": "2026-06-15",
      "id": "00000000-0000-4000-8000-000000000000",
      "refCollectionTask": null,
      "dataUpdateTime": "2026-06-25T00:00",
      "contentSummary": "测试舰艇064印太司令部2025年8月公开材料显示测试水面舰044测试母港F访问/活动记录。",
      "publishTime": "2025-08-01T00:00",
      "relatedEvent": null,
      "socialAccount": null,
      "typeCode": null,
      "catCode": "MediaReport",
      "eventTrend": null,
      "isSimulationData": null,
      "subordinateTo": null,
      "updateSeqnr": null,
      "name": "PACOM发布CVN-T10 2025年8月测试母港F活动新闻截图二",
      "publisher": null,
      "keywordTags": "CVN-T10,USS 测试舰,测试水面舰044,测试母港A,测试海区己,测试母港F,2026年部署,OSINT,PACOM,测试母港F,历史活动"
    },
    {
      "rawDataBlockPtr": null,
      "relatedPlatform": "CVN-T02",
      "reliability": "中高",
      "creatorId": null,
      "curStatus": null,
      "confidentialityLevel": null,
      "sourceUrl": "",
      "influenceType": null,
      "sourceOrigin": null,
      "credibilityScore": null,
      "imageUrl": null,
      "sourcePlatform": "OSINT_CARRIER_ACTIVITY_2020_2026",
      "startTime": "2026-06-15",
      "id": "00000000-0000-4000-8000-000000000000",
      "refCollectionTask": null,
      "dataUpdateTime": "2026-06-16T00:00",
      "contentSummary": "时间段 ：① 2025 下半年（约 12 月）在测试海区丁作业（事件1.md 口径，为 2026/1 转赴测试陆域甲前序）。；活动 ：① 飞行作业与巡航，强化区域稳定。；停靠 ：未披露。；天气 ：无逐次公开数据。；补给 ：无逐次公开合同。；参演 1）人员：CSG-T02、CVW-T 人员。 2）船、飞机：测试舰CN37 CSG（CVW-T）。 参演国家：测试舰艇064。；护航编成表 1）舰船表：①公开有限。 2）飞机表：①第9舰载机联队（CVW-T）。",
      "publishTime": "2026-01-01T00:00",
      "relatedEvent": null,
      "socialAccount": null,
      "typeCode": null,
      "catCode": "MediaReport",
      "eventTrend": null,
      "isSimulationData": null,
      "subordinateTo": null,
      "updateSeqnr": null,
      "name": "CVN-T02 测试航母12：2025 下半年 测试海区丁行动",
      "publisher": null,
      "keywordTags": "CVN-T02,测试航母12,测试舰艇064航母,测试海区丁,西测试海区甲,印太部署,2020-2026,OSINT"
    },
    {
      "rawDataBlockPtr": null,
      "relatedPlatform": "CVN-T10",
      "reliability": "中高",
      "creatorId": null,
      "curStatus": null,
      "confidentialityLevel": null,
      "sourceUrl": null,
      "influenceType": null,
      "sourceOrigin": null,
      "credibilityScore": null,
      "imageUrl": "",
      "sourcePlatform": "JAPAN_MOFA",
      "startTime": "2026-06-15",
      "id": "00000000-0000-4000-8000-000000000000",
      "refCollectionTask": null,
      "dataUpdateTime": "2026-06-22T00:00",
      "contentSummary": "公开通报显示测试水面舰044于2026-05-10 09:53从测试母港A港出发进行海试，测试员147Nicholas Deleo，船员约3114人。",
      "publishTime": "2026-05-10T09:53",
      "relatedEvent": null,
      "socialAccount": null,
      "typeCode": null,
      "catCode": "MediaReport",
      "eventTrend": null,
      "isSimulationData": null,
      "subordinateTo": null,
      "updateSeqnr": null,
      "name": "日本公开通报CVN-T10于5月10日海试离港",
      "publisher": null,
      "keywordTags": "CVN-T10,USS 测试舰,测试水面舰044,测试母港A,测试海区己,测试母港F,2026年部署,OSINT,日本通报,海试,测试母港A"
    },
    {
      "rawDataBlockPtr": null,
      "relatedPlatform": "CVN-T10",
      "reliability": "中高",
      "creatorId": null,
      "curStatus": null,
      "confidentialityLevel": null,
      "sourceUrl": null,
      "influenceType": null,
      "sourceOrigin": null,
      "credibilityScore": null,
      "imageUrl": "",
      "sourcePlatform": null,
      "startTime": "2026-06-15",
      "id": "00000000-0000-4000-8000-000000000000",
      "refCollectionTask": null,
      "dataUpdateTime": "2026-06-25T00:00",
      "contentSummary": "X用户Virtual于2026-05-26发布2026-05-25 VFA-147 F-35C在测试海区己从CVN-T10起降照片，表明航母正在测试海区己飞行作业。",
      "publishTime": "2026-05-26T00:00",
      "relatedEvent": null,
      "socialAccount": "source26",
      "typeCode": null,
      "catCode": "MediaReport",
      "eventTrend": null,
      "isSimulationData": null,
      "subordinateTo": null,
      "updateSeqnr": null,
      "name": "Virtual发布VFA-147 F-35C在测试海区己从CVN-T10起降",
      "publisher": null,
      "keywordTags": "CVN-T10,USS 测试舰,测试水面舰044,测试母港A,测试海区己,测试母港F,2026年部署,OSINT,X,VFA-147,F-35C,测试海区己"
    },
    {
      "rawDataBlockPtr": null,
      "relatedPlatform": "CVN-T10",
      "reliability": "中高",
      "creatorId": null,
      "curStatus": null,
      "confidentialityLevel": null,
      "sourceUrl": null,
      "influenceType": null,
      "sourceOrigin": null,
      "credibilityScore": null,
      "imageUrl": "",
      "sourcePlatform": "AIS_TRACKER",
      "startTime": "2026-06-15",
      "id": "00000000-0000-4000-8000-000000000000",
      "refCollectionTask": null,
      "dataUpdateTime": "2026-06-19T00:00",
      "contentSummary": "AIS记录显示CVN-T10（MMSI 999000008）从2026-05-20 22:46停泊测试母港A，到2026-05-23 13:28沿航道离港，航速约8.3节。",
      "publishTime": "2026-05-23T13:28",
      "relatedEvent": null,
      "socialAccount": null,
      "typeCode": null,
      "catCode": "MediaReport",
      "eventTrend": null,
      "isSimulationData": null,
      "subordinateTo": null,
      "updateSeqnr": null,
      "name": "AIS捕获CVN-T10从测试母港A出港轨迹",
      "publisher": null,
      "keywordTags": "CVN-T10,USS 测试舰,测试水面舰044,测试母港A,测试海区己,测试母港F,2026年部署,OSINT,AIS,MMSI999000008,出港轨迹"
    },
    {
      "rawDataBlockPtr": null,
      "relatedPlatform": "CVN-T10",
      "reliability": "中高",
      "creatorId": null,
      "curStatus": null,
      "confidentialityLevel": null,
      "sourceUrl": null,
      "influenceType": null,
      "sourceOrigin": null,
      "credibilityScore": null,
      "imageUrl": "",
      "sourcePlatform": "SATELLITE_IMAGERY",
      "startTime": "2026-06-16",
      "id": "00000000-0000-4000-8000-000000000000",
      "refCollectionTask": null,
      "dataUpdateTime": "2026-06-21T00:00",
      "contentSummary": "正式部署前卫星影像显示CVN-T10回到测试母港A12号码头停泊。",
      "publishTime": "2026-05-20T00:00",
      "relatedEvent": null,
      "socialAccount": null,
      "typeCode": null,
      "catCode": "MediaReport",
      "eventTrend": null,
      "isSimulationData": null,
      "subordinateTo": null,
      "updateSeqnr": null,
      "name": "2026-06-16 测试母港A12号码头卫星图显示CVN-T10在港",
      "publisher": null,
      "keywordTags": "CVN-T10,USS 测试舰,测试水面舰044,测试母港A,测试海区己,测试母港F,2026年部署,OSINT,卫星影像,出港前"
    },
    {
      "rawDataBlockPtr": null,
      "relatedPlatform": "CVN-T10",
      "reliability": "中高",
      "creatorId": null,
      "curStatus": null,
      "confidentialityLevel": null,
      "sourceUrl": "",
      "influenceType": null,
      "sourceOrigin": null,
      "credibilityScore": null,
      "imageUrl": null,
      "sourcePlatform": "OSINT_CARRIER_ACTIVITY_2020_2026",
      "startTime": "2026-06-15",
      "id": "00000000-0000-4000-8000-000000000000",
      "refCollectionTask": null,
      "dataUpdateTime": "2026-06-16T00:00",
      "contentSummary": "时间段 ① 2024/4–7 月 南美周边（非印太）部署，后转赴日本换防。；活动 ① Southern Seas 2024——与拉美/加勒比盟国联合演习与通过演练（航行展示、伙伴交流），系赴日前最后一段本土序列部署。；停靠 ：①南美沿途港口（公开有限）。；天气 ：无逐次公开数据；跨热带/温带海区。；补给 ：公开关联补给舰 USNS 测试舰（T-AO-189） 。；参演 1）人员：CSG 主力、CVW-T 人员。 2）船、飞机：测试航母10（ CVW-T ）；护航测试舰艇097 DDG-T55、测试舰艇038 DDG-T17。 参演国家：测试舰艇064及拉美/加勒比伙伴。；护航编成表 1）舰船表：①测试舰艇097 DDG-T55；②测试舰艇038 DDG-T17。 2）飞机表：①第7舰载机联队（CVW-T，此阶段配属）。",
      "publishTime": "2024-04-01T00:00",
      "relatedEvent": null,
      "socialAccount": null,
      "typeCode": null,
      "catCode": "MediaReport",
      "eventTrend": null,
      "isSimulationData": null,
      "subordinateTo": null,
      "updateSeqnr": null,
      "name": "CVN-T10 测试水面舰044：2024/4–7 Southern Seas 2024（南美方向，赴日换防前）",
      "publisher": null,
      "keywordTags": "CVN-T10,测试水面舰044,测试舰艇064航母,测试海区丁,西测试海区甲,印太部署,2020-2026,OSINT"
    },
    {
      "rawDataBlockPtr": null,
      "relatedPlatform": "CVN-T08",
      "reliability": "中",
      "creatorId": null,
      "curStatus": null,
      "confidentialityLevel": null,
      "sourceUrl": "",
      "influenceType": null,
      "sourceOrigin": null,
      "credibilityScore": null,
      "imageUrl": null,
      "sourcePlatform": "OSINT_CARRIER_ACTIVITY_2020_2026",
      "startTime": "2026-06-15",
      "id": "00000000-0000-4000-8000-000000000000",
      "refCollectionTask": null,
      "dataUpdateTime": "2026-06-15T00:00",
      "contentSummary": "时间段 ① 2021/6/14 本年部署首次进入测试海区丁（测试来源甲记测试海区丁+巴拉望以西 6/14–7/5）。 ② 2021/6/26 部署测试陆域甲，支援美军自阿富汗撤离；10 月返航。 ③ 2021/9/24 ⚠️返航后再入测试海区丁，进行固定/旋翼飞行作业、海上打击、反潜与战术训练（事件1.md 口径，与测试陆域甲任务时序存疑）。；活动 ① 海上安全行动、飞行行动、舰载电子战机（EA-18G）实战化训练、盟友海上协同；② 转赴测试陆域甲支援撤离行动。；停靠 ：①⚠️测试来源甲记马来西亚巴生港（6/28–7/02，英文主流以测试陆域甲转向为主线）。；天气 ：无逐次公开数据；测试海区丁 6 月西南季风/雨季、阵雨雷暴、热带扰动概率高。；补给 ：无逐次公开合同；⚠️测试来源甲记巴生港油料由 BP 马来西亚、海上 MSC 补给舰随行（英文主流未确认）。；参演 1）人员：⚠️存疑\"第5打击群指挥官迈克尔·多诺万少将\"（仅测试来源甲）。 2）船、飞机：测试舰CN05 CSG（CVW-T）。 参演国家：测试舰艇064（主），⚠️测试来源甲补充马来西亚、菲律宾。；护航编成表 1）舰船表：①夏伊洛 CG-T13（巡洋舰，2021/9 公开）；②DESRON-15 属舰。 2）飞机表：①第5舰载机联队（CVW-T），含 EA-18G。",
      "publishTime": "2021-06-14T00:00",
      "relatedEvent": null,
      "socialAccount": null,
      "typeCode": null,
      "catCode": "MediaReport",
      "eventTrend": null,
      "isSimulationData": null,
      "subordinateTo": null,
      "updateSeqnr": null,
      "name": "CVN-T08 测试航母07：2021/6 测试海区丁行动与测试陆域甲支援",
      "publisher": null,
      "keywordTags": "CVN-T08,测试航母07,测试舰艇064航母,测试海区丁,西测试海区甲,印太部署,2020-2026,OSINT"
    },
    {
      "rawDataBlockPtr": null,
      "relatedPlatform": "CVN-T10",
      "reliability": "中高",
      "creatorId": null,
      "curStatus": null,
      "confidentialityLevel": null,
      "sourceUrl": null,
      "influenceType": null,
      "sourceOrigin": null,
      "credibilityScore": null,
      "imageUrl": "",
      "sourcePlatform": "FLIGHTRADAR24",
      "startTime": "2026-06-21",
      "id": "00000000-0000-4000-8000-000000000000",
      "refCollectionTask": null,
      "dataUpdateTime": "2026-06-13T00:00",
      "contentSummary": "Flightradar24于2026-05-30捕获RUDY73/RUDY70自测试海区己方向北飞至岩国，南端起点指向航母所在海域。",
      "publishTime": "2026-05-30T00:00",
      "relatedEvent": null,
      "socialAccount": null,
      "typeCode": null,
      "catCode": "MediaReport",
      "eventTrend": null,
      "isSimulationData": null,
      "subordinateTo": null,
      "updateSeqnr": null,
      "name": "Flightradar24捕获RUDY73/RUDY70飞往岩国航迹",
      "publisher": null,
      "keywordTags": "CVN-T10,USS 测试舰,测试水面舰044,测试母港A,测试海区己,测试母港F,2026年部署,OSINT,Flightradar24,RUDY70,RUDY73,岩国"
    },
    {
      "rawDataBlockPtr": null,
      "relatedPlatform": "CVN-T10",
      "reliability": "中高",
      "creatorId": null,
      "curStatus": null,
      "confidentialityLevel": null,
      "sourceUrl": null,
      "influenceType": null,
      "sourceOrigin": null,
      "credibilityScore": null,
      "imageUrl": "",
      "sourcePlatform": "ADSB_TRACKER",
      "startTime": "2026-06-23",
      "id": "00000000-0000-4000-8000-000000000000",
      "refCollectionTask": null,
      "dataUpdateTime": "2026-06-23T00:00",
      "contentSummary": "综合CVN-T10连续位置、AA0003直升机、护航舰测试水面舰005、无人艇SD-3002和2025年历史训练区，验证航母位于测试母港F以西。",
      "publishTime": "2026-06-03T00:00",
      "relatedEvent": null,
      "socialAccount": null,
      "typeCode": null,
      "catCode": "MediaReport",
      "eventTrend": null,
      "isSimulationData": null,
      "subordinateTo": null,
      "updateSeqnr": null,
      "name": "测试母港F以西CVN-T10及伴随目标综合态势图",
      "publisher": null,
      "keywordTags": "CVN-T10,USS 测试舰,测试水面舰044,测试母港A,测试海区己,测试母港F,2026年部署,OSINT,测试母港F以西,综合态势,闭环验证"
    },
    {
      "rawDataBlockPtr": null,
      "relatedPlatform": "CVN-T10",
      "reliability": "中高",
      "creatorId": null,
      "curStatus": null,
      "confidentialityLevel": null,
      "sourceUrl": null,
      "influenceType": null,
      "sourceOrigin": null,
      "credibilityScore": null,
      "imageUrl": "",
      "sourcePlatform": "SATELLITE_IMAGERY",
      "startTime": "2026-06-15",
      "id": "00000000-0000-4000-8000-000000000000",
      "refCollectionTask": null,
      "dataUpdateTime": "2026-06-24T00:00",
      "contentSummary": "出港前窗口期卫星影像显示CVN-T10仍在测试母港A12号码头。",
      "publishTime": "2026-05-08T00:00",
      "relatedEvent": null,
      "socialAccount": null,
      "typeCode": null,
      "catCode": "MediaReport",
      "eventTrend": null,
      "isSimulationData": null,
      "subordinateTo": null,
      "updateSeqnr": null,
      "name": "2026-05-08 测试母港A12号码头卫星图显示CVN-T10在港",
      "publisher": null,
      "keywordTags": "CVN-T10,USS 测试舰,测试水面舰044,测试母港A,测试海区己,测试母港F,2026年部署,OSINT,卫星影像,出港前"
    },
    {
      "rawDataBlockPtr": null,
      "relatedPlatform": "CVN-T10",
      "reliability": "中高",
      "creatorId": null,
      "curStatus": null,
      "confidentialityLevel": null,
      "sourceUrl": null,
      "influenceType": null,
      "sourceOrigin": null,
      "credibilityScore": null,
      "imageUrl": "",
      "sourcePlatform": "AIS_TRACKER",
      "startTime": "2026-06-15",
      "id": "00000000-0000-4000-8000-000000000000",
      "refCollectionTask": null,
      "dataUpdateTime": "2026-06-13T00:00",
      "contentSummary": "AIS显示DDG-T05于2026-05-28位于132.21E/30.19N附近，航速约17节，进一步印证编队向日本西南方向推进。",
      "publishTime": "2026-05-28T00:00",
      "relatedEvent": null,
      "socialAccount": null,
      "typeCode": null,
      "catCode": "MediaReport",
      "eventTrend": null,
      "isSimulationData": null,
      "subordinateTo": null,
      "updateSeqnr": null,
      "name": "DDG-T05测试水面舰066位于日本西南方向AIS航迹",
      "publisher": null,
      "keywordTags": "CVN-T10,USS 测试舰,测试水面舰044,测试母港A,测试海区己,测试母港F,2026年部署,OSINT,AIS,DDG-T05,护航舰"
    },
    {
      "rawDataBlockPtr": null,
      "relatedPlatform": "CVN-T10",
      "reliability": "中",
      "creatorId": null,
      "curStatus": null,
      "confidentialityLevel": null,
      "sourceUrl": null,
      "influenceType": null,
      "sourceOrigin": null,
      "credibilityScore": null,
      "imageUrl": "",
      "sourcePlatform": null,
      "startTime": "2026-06-15",
      "id": "00000000-0000-4000-8000-000000000000",
      "refCollectionTask": null,
      "dataUpdateTime": "2026-06-18T00:00",
      "contentSummary": "整理VFA-102、VFA-27、VFA-147、VFA-195、VAQ-141、VAW-125、HSC-12、HSM-77、VRM-30 Det.5等CVW-T主要中队。",
      "publishTime": "2026-05-23T00:00",
      "relatedEvent": null,
      "socialAccount": null,
      "typeCode": null,
      "catCode": "MediaReport",
      "eventTrend": null,
      "isSimulationData": null,
      "subordinateTo": null,
      "updateSeqnr": null,
      "name": "CVW-T本次随舰部署中队编成清单",
      "publisher": null,
      "keywordTags": "CVN-T10,USS 测试舰,测试水面舰044,测试母港A,测试海区己,测试母港F,2026年部署,OSINT,CVW-T,编成"
    },
    {
      "rawDataBlockPtr": null,
      "relatedPlatform": "CVN-T10",
      "reliability": "中高",
      "creatorId": null,
      "curStatus": null,
      "confidentialityLevel": null,
      "sourceUrl": null,
      "influenceType": null,
      "sourceOrigin": null,
      "credibilityScore": null,
      "imageUrl": "",
      "sourcePlatform": "ADSB_TRACKER",
      "startTime": "2026-06-15",
      "id": "00000000-0000-4000-8000-000000000000",
      "refCollectionTask": null,
      "dataUpdateTime": "2026-06-19T00:00",
      "contentSummary": "ADS-B公开数据识别AEEBA3为V-22/注册号169450，为定位CVN-T10伴随机提供目标基础信息。",
      "publishTime": "2026-05-30T21:00",
      "relatedEvent": null,
      "socialAccount": null,
      "typeCode": null,
      "catCode": "MediaReport",
      "eventTrend": null,
      "isSimulationData": null,
      "subordinateTo": null,
      "updateSeqnr": null,
      "name": "ADS-B目标AEEBA3信息截图",
      "publisher": null,
      "keywordTags": "CVN-T10,USS 测试舰,测试水面舰044,测试母港A,测试海区己,测试母港F,2026年部署,OSINT,ADS-B,AEEBA3,V-22"
    },
    {
      "rawDataBlockPtr": null,
      "relatedPlatform": "CVN-T10",
      "reliability": "中高",
      "creatorId": null,
      "curStatus": null,
      "confidentialityLevel": null,
      "sourceUrl": "",
      "influenceType": null,
      "sourceOrigin": null,
      "credibilityScore": null,
      "imageUrl": "",
      "sourcePlatform": "USNIN",
      "startTime": "2026-06-15",
      "id": "00000000-0000-4000-8000-000000000000",
      "refCollectionTask": null,
      "dataUpdateTime": "2026-06-13T00:00",
      "contentSummary": "USNI Fleet and Marine Tracker于2026-05-26发布舰队周报，提供CVN-T10部署态势公开背景。",
      "publishTime": "2026-05-26T00:00",
      "relatedEvent": null,
      "socialAccount": null,
      "typeCode": null,
      "catCode": "MediaReport",
      "eventTrend": null,
      "isSimulationData": null,
      "subordinateTo": null,
      "updateSeqnr": null,
      "name": "USNI Fleet and Marine Tracker 2026-05-26更新",
      "publisher": null,
      "keywordTags": "CVN-T10,USS 测试舰,测试水面舰044,测试母港A,测试海区己,测试母港F,2026年部署,OSINT,USNI,Fleet Tracker"
    },
    {
      "rawDataBlockPtr": null,
      "relatedPlatform": "CVN-T10",
      "reliability": "中高",
      "creatorId": null,
      "curStatus": null,
      "confidentialityLevel": null,
      "sourceUrl": "",
      "influenceType": null,
      "sourceOrigin": null,
      "credibilityScore": null,
      "imageUrl": "",
      "sourcePlatform": "USINDOPACOM",
      "startTime": "2026-06-15",
      "id": "00000000-0000-4000-8000-000000000000",
      "refCollectionTask": null,
      "dataUpdateTime": "2026-06-24T00:00",
      "contentSummary": "测试舰艇064印太司令部2025年8月公开新闻显示CVN-T10在测试母港F相关活动，为研判测试母港F周边历史活动规律提供依据。",
      "publishTime": "2025-08-01T00:00",
      "relatedEvent": null,
      "socialAccount": null,
      "typeCode": null,
      "catCode": "MediaReport",
      "eventTrend": null,
      "isSimulationData": null,
      "subordinateTo": null,
      "updateSeqnr": null,
      "name": "PACOM发布CVN-T10 2025年8月测试母港F活动新闻截图一",
      "publisher": null,
      "keywordTags": "CVN-T10,USS 测试舰,测试水面舰044,测试母港A,测试海区己,测试母港F,2026年部署,OSINT,PACOM,测试母港F,历史活动"
    },
    {
      "rawDataBlockPtr": null,
      "relatedPlatform": null,
      "reliability": null,
      "creatorId": null,
      "curStatus": "PUBLISHED",
      "confidentialityLevel": null,
      "sourceUrl": "",
      "influenceType": "POSITIVE",
      "sourceOrigin": null,
      "credibilityScore": null,
      "imageUrl": null,
      "sourcePlatform": "DVIDS",
      "startTime": null,
      "id": "OSINT_NICHOLAS_DELEO_005",
      "refCollectionTask": null,
      "dataUpdateTime": "2026-06-20T00:00",
      "contentSummary": "在测试母港A举行的交接仪式中正式接任测试航母10测试员147，公开表态继续推进前沿部署航母战备与印太地区行动。",
      "publishTime": "2026-03-13T00:00",
      "relatedEvent": null,
      "socialAccount": null,
      "typeCode": null,
      "catCode": "MediaReport",
      "eventTrend": null,
      "isSimulationData": null,
      "subordinateTo": null,
      "updateSeqnr": null,
      "name": "接任测试舰CN35号航母测试员147",
      "publisher": "source24",
      "keywordTags": "测试舰CN35号航母,CSG-T10,前沿部署,印太地区,航母战备"
    },
    {
      "rawDataBlockPtr": null,
      "relatedPlatform": "CVN-T01",
      "reliability": "中高",
      "creatorId": null,
      "curStatus": null,
      "confidentialityLevel": null,
      "sourceUrl": "",
      "influenceType": null,
      "sourceOrigin": null,
      "credibilityScore": null,
      "imageUrl": null,
      "sourcePlatform": "OSINT_CARRIER_ACTIVITY_2020_2026",
      "startTime": "2026-06-15",
      "id": "00000000-0000-4000-8000-000000000000",
      "refCollectionTask": null,
      "dataUpdateTime": "2026-06-23T00:00",
      "contentSummary": "时间段 ① 2023/12/15–12/25 前后（测试海区丁+测试港城乙，12 月中下旬连续活动）。；活动 ① 测试港城乙访后返回测试海区丁；海上行动与补给照片公开。；停靠 ：①测试港城乙（12 月中下旬，时长未完整披露）。；天气 ：无逐次公开数据；测试港城乙 12 月东北季风湿季，降雨频繁、雷阵雨常见。；补给 ： 公开影像 显示与 USNS 测试舰（T-AKE-8） 进行海上补给/货物转运；运营体系为 MSC，商业供应商未披露。；参演 1）人员：CSG-T01、CVW-T 人员。 2）船、飞机：测试舰CN02 CSG；护航含 USS 测试舰 、 USS 测试舰 、 USS 测试舰 。 参演国家：测试舰艇064、测试港城乙。；护航编成表 1）舰船表：①测试舰EN13（CG）；②测试舰EN173（DDG）；③测试舰EN27（DDG）。 2）飞机表：①第2舰载机联队（CVW-T）。",
      "publishTime": "2023-12-15T00:00",
      "relatedEvent": null,
      "socialAccount": null,
      "typeCode": null,
      "catCode": "MediaReport",
      "eventTrend": null,
      "isSimulationData": null,
      "subordinateTo": null,
      "updateSeqnr": null,
      "name": "CVN-T01 测试航母11：2023/12 测试港城乙—测试海区丁行动",
      "publisher": null,
      "keywordTags": "CVN-T01,测试航母11,测试舰艇064航母,测试海区丁,西测试海区甲,印太部署,2020-2026,OSINT"
    },
    {
      "rawDataBlockPtr": null,
      "relatedPlatform": "CVN-T10",
      "reliability": "中高",
      "creatorId": null,
      "curStatus": null,
      "confidentialityLevel": null,
      "sourceUrl": "",
      "influenceType": null,
      "sourceOrigin": null,
      "credibilityScore": null,
      "imageUrl": "",
      "sourcePlatform": "USNIN",
      "startTime": "2026-06-15",
      "id": "00000000-0000-4000-8000-000000000000",
      "refCollectionTask": null,
      "dataUpdateTime": "2026-06-17T00:00",
      "contentSummary": "USNI News于2026-05-26报道测试水面舰044离开测试母港A准备春季巡逻，并与区域航母活动态势相关联。",
      "publishTime": "2026-05-26T00:00",
      "relatedEvent": null,
      "socialAccount": null,
      "typeCode": null,
      "catCode": "MediaReport",
      "eventTrend": null,
      "isSimulationData": null,
      "subordinateTo": null,
      "updateSeqnr": null,
      "name": "USNI报道辽宁号接近菲律宾且CVN-T10离开测试母港A春巡",
      "publisher": null,
      "keywordTags": "CVN-T10,USS 测试舰,测试水面舰044,测试母港A,测试海区己,测试母港F,2026年部署,OSINT,USNI,春季巡逻"
    },
    {
      "rawDataBlockPtr": null,
      "relatedPlatform": "CVN-T10",
      "reliability": "中高",
      "creatorId": null,
      "curStatus": null,
      "confidentialityLevel": null,
      "sourceUrl": null,
      "influenceType": null,
      "sourceOrigin": null,
      "credibilityScore": null,
      "imageUrl": "",
      "sourcePlatform": null,
      "startTime": "2026-06-15",
      "id": "00000000-0000-4000-8000-000000000000",
      "refCollectionTask": null,
      "dataUpdateTime": "2026-06-12T00:00",
      "contentSummary": "X用户Cheyanne Kin于2026-04-02发布“测试母港F Once again for my Last Det”，指向VFA-102相关人员测试母港F分遣活动。",
      "publishTime": "2026-04-02T00:00",
      "relatedEvent": null,
      "socialAccount": "source27",
      "typeCode": null,
      "catCode": "MediaReport",
      "eventTrend": null,
      "isSimulationData": null,
      "subordinateTo": null,
      "updateSeqnr": null,
      "name": "Cheyanne Kin发布VFA-102测试母港F分遣训练动态",
      "publisher": null,
      "keywordTags": "CVN-T10,USS 测试舰,测试水面舰044,测试母港A,测试海区己,测试母港F,2026年部署,OSINT,X,VFA-102,测试母港F分遣"
    },
    {
      "rawDataBlockPtr": null,
      "relatedPlatform": "CVN-T10",
      "reliability": "中高",
      "creatorId": null,
      "curStatus": null,
      "confidentialityLevel": null,
      "sourceUrl": null,
      "influenceType": null,
      "sourceOrigin": null,
      "credibilityScore": null,
      "imageUrl": "",
      "sourcePlatform": "JAPAN_MOFA",
      "startTime": "2026-06-18",
      "id": "00000000-0000-4000-8000-000000000000",
      "refCollectionTask": null,
      "dataUpdateTime": "2026-06-12T00:00",
      "contentSummary": "变更通知将CVN-T10出发日修订为2026-05-23 10:00左右，锁定正式出港窗口。",
      "publishTime": "2026-05-21T00:00",
      "relatedEvent": null,
      "socialAccount": null,
      "typeCode": null,
      "catCode": "MediaReport",
      "eventTrend": null,
      "isSimulationData": null,
      "subordinateTo": null,
      "updateSeqnr": null,
      "name": "日本公开通报CVN-T10出港时间变更为6月20日",
      "publisher": null,
      "keywordTags": "CVN-T10,USS 测试舰,测试水面舰044,测试母港A,测试海区己,测试母港F,2026年部署,OSINT,日本通报,出港改期"
    },
    {
      "rawDataBlockPtr": null,
      "relatedPlatform": "CVN-T10",
      "reliability": "中高",
      "creatorId": null,
      "curStatus": null,
      "confidentialityLevel": null,
      "sourceUrl": "",
      "influenceType": null,
      "sourceOrigin": null,
      "credibilityScore": null,
      "imageUrl": null,
      "sourcePlatform": "OSINT_CARRIER_ACTIVITY_2020_2026",
      "startTime": "2026-06-15",
      "id": "00000000-0000-4000-8000-000000000000",
      "refCollectionTask": null,
      "dataUpdateTime": "2026-06-12T00:00",
      "contentSummary": "时间段 ① 2026/5 下旬—6 初 从日本出发的新一轮印太部署/巡逻，在测试海区己活动。；活动 ：① 新一轮印太部署/巡逻（不扩展未公开实时动向）。；停靠 ：①日本测试母港A出港线索；港访未披露。；天气 ：无逐次公开数据；测试海区己 6 月湿热、雨季和台风季开始。；补给 ：无逐次公开合同（不推断后续补给计划）。；参演 1）人员：前沿部署航母舰员、CVW-T。 2）船、飞机：测试航母10 CSG（CVW-T）。 参演国家：测试舰艇064、日本前沿基地体系。；护航编成表 1）舰船表：①公开有限（罗伯特·斯莫斯 CG-T02、舒普 DDG-T05 等 DESRON-15 属舰）。 2）飞机表：①第5舰载机联队（CVW-T）。",
      "publishTime": "2026-05-01T00:00",
      "relatedEvent": null,
      "socialAccount": null,
      "typeCode": null,
      "catCode": "MediaReport",
      "eventTrend": null,
      "isSimulationData": null,
      "subordinateTo": null,
      "updateSeqnr": null,
      "name": "CVN-T10 测试水面舰044：2026/5–6 新一轮印太部署（窗口末端）",
      "publisher": null,
      "keywordTags": "CVN-T10,测试水面舰044,测试舰艇064航母,测试海区丁,西测试海区甲,印太部署,2020-2026,OSINT"
    },
    {
      "rawDataBlockPtr": null,
      "relatedPlatform": "CVN-T10",
      "reliability": "中高",
      "creatorId": null,
      "curStatus": null,
      "confidentialityLevel": null,
      "sourceUrl": null,
      "influenceType": null,
      "sourceOrigin": null,
      "credibilityScore": null,
      "imageUrl": "",
      "sourcePlatform": "SATELLITE_IMAGERY",
      "startTime": "2026-06-15",
      "id": "00000000-0000-4000-8000-000000000000",
      "refCollectionTask": null,
      "dataUpdateTime": "2026-06-21T00:00",
      "contentSummary": "卫星影像显示测试水面舰044不在测试母港A12号码头，作为后续在港/离港基线比对。",
      "publishTime": "2025-12-07T00:00",
      "relatedEvent": null,
      "socialAccount": null,
      "typeCode": null,
      "catCode": "MediaReport",
      "eventTrend": null,
      "isSimulationData": null,
      "subordinateTo": null,
      "updateSeqnr": null,
      "name": "2025-12-07 测试母港A12号码头卫星图显示CVN-T10不在港",
      "publisher": null,
      "keywordTags": "CVN-T10,USS 测试舰,测试水面舰044,测试母港A,测试海区己,测试母港F,2026年部署,OSINT,卫星影像,在港基线"
    },
    {
      "rawDataBlockPtr": null,
      "relatedPlatform": "CVN-T10",
      "reliability": "中高",
      "creatorId": null,
      "curStatus": null,
      "confidentialityLevel": null,
      "sourceUrl": null,
      "influenceType": null,
      "sourceOrigin": null,
      "credibilityScore": null,
      "imageUrl": "",
      "sourcePlatform": "AIS_TRACKER",
      "startTime": "2026-06-23",
      "id": "00000000-0000-4000-8000-000000000000",
      "refCollectionTask": null,
      "dataUpdateTime": "2026-06-26T00:00",
      "contentSummary": "AIS显示T-AO-207自2026-05-26由日本近海南下穿越测试海区己，向测试母港F方向航行。",
      "publishTime": "2026-06-03T08:03",
      "relatedEvent": null,
      "socialAccount": null,
      "typeCode": null,
      "catCode": "MediaReport",
      "eventTrend": null,
      "isSimulationData": null,
      "subordinateTo": null,
      "updateSeqnr": null,
      "name": "T-AO-207自日本南下测试海区己AIS航迹",
      "publisher": null,
      "keywordTags": "CVN-T10,USS 测试舰,测试水面舰044,测试母港A,测试海区己,测试母港F,2026年部署,OSINT,AIS,T-AO-207,测试海区己"
    },
    {
      "rawDataBlockPtr": null,
      "relatedPlatform": "CVN-T09",
      "reliability": "中",
      "creatorId": null,
      "curStatus": null,
      "confidentialityLevel": null,
      "sourceUrl": "",
      "influenceType": null,
      "sourceOrigin": null,
      "credibilityScore": null,
      "imageUrl": null,
      "sourcePlatform": "OSINT_CARRIER_ACTIVITY_2020_2026",
      "startTime": "2026-06-15",
      "id": "00000000-0000-4000-8000-000000000000",
      "refCollectionTask": null,
      "dataUpdateTime": "2026-06-24T00:00",
      "contentSummary": "时间段 ① 2025/3/21 自测试母港D/测试母港B启航（末次全球部署）。 ② 2025/3/24–3/27 测试母港F阿普拉港访。 ③ 2025/3/31 经巴士海峡入测试海区丁，测试海区丁 3/31–4/3（约 4 天），4/4 过测试港城乙海峡赴测试陆域甲。 ④ 2025/5 月 测试海区己训练后再入测试海区丁；6/11 测试海区丁例行飞行行动。 ⑤ 2025/6/18–20 因以伊冲突升级，经马六甲西出测试海区丙赴测试陆域甲（ 原定 6/20 越南岘港港访临时取消 ）。 ⑥ 2025/10/17 结束测试陆域甲约 3 个月任务，经测试港城乙海峡重回测试海区丁，10/21 进入测试海区丁，与测试舰CN35 CSG 短暂会合。 ⑦ 2025/11/17 经吕宋海峡驶出测试海区丁（本阶段测试海区丁约 32 天）。；活动 ① 例行飞行/海上行动；② 2025/10/21–26 美马（测试舰艇064—马来西亚）双边演习；③ 2025/11/14–15 美日菲测试海区丁联合军演（9 艘舰艇参演，测试来源甲口径）。；停靠 ① 测试母港F阿普拉（3/24–3/27）。 ② 马来西亚巴生港（10/28–11/1，测试来源甲口径；⚠️Claude 标注巴生港时点存疑）。 ③ 越南岘港（原定 6/20， 已取消 ）。；天气 ：无逐次公开数据；春季测试海区丁多云偏东风；10 月测试海区丁秋高气爽、偶有局部阵雨。；补给 ：无逐次公开合同；⚠️测试来源甲记 T-AO-205\"约翰·刘易斯号\"油轮全程伴随（具体补给计划未公开）。；参演 1）人员：测试舰CN01 CSG、舰载机联队人员（普通名单不公开）。 2）船、飞机：测试舰CN01 CSG； 事故 ：2025/10/26 测试海区丁一架 F/A-18F 战机、一架 MH-60R 直升机先后坠海，机组全部获救。 参演国家：测试舰艇064、马来西亚、日本、菲律宾。；护航编成表 1）舰船表：①本阶段护航属舰公开有限（未系统披露）。 2）飞机表：①舰载机联队（含 F/A-18E/F、MH-60R 等）。",
      "publishTime": "2025-03-21T00:00",
      "relatedEvent": null,
      "socialAccount": null,
      "typeCode": null,
      "catCode": "MediaReport",
      "eventTrend": null,
      "isSimulationData": null,
      "subordinateTo": null,
      "updateSeqnr": null,
      "name": "CVN-T09 测试航母03：2025 年 末次全球部署（退役前）",
      "publisher": null,
      "keywordTags": "CVN-T09,测试航母03,测试舰艇064航母,测试海区丁,西测试海区甲,印太部署,2020-2026,OSINT"
    },
    {
      "rawDataBlockPtr": null,
      "relatedPlatform": "CVN-T01",
      "reliability": "中高",
      "creatorId": null,
      "curStatus": null,
      "confidentialityLevel": null,
      "sourceUrl": "",
      "influenceType": null,
      "sourceOrigin": null,
      "credibilityScore": null,
      "imageUrl": null,
      "sourcePlatform": "OSINT_CARRIER_ACTIVITY_2020_2026",
      "startTime": "2026-06-15",
      "id": "00000000-0000-4000-8000-000000000000",
      "refCollectionTask": null,
      "dataUpdateTime": "2026-06-26T00:00",
      "contentSummary": "时间段 ① 2025/3 测试港城甲 5 天港访后转测试海区庚；CVW-T 在测试母港F演练。 ② 2025/3/17–3/20 美日韩三边海上演习（测试海区戊/日本周边）。 ③ 2025/4/4 前后 经马六甲海峡转向测试陆域甲（穿越测试海区丁，中方山东舰同期演训）。 ④ 2025/8/14 返回测试母港B母港，结束约 9 个月部署周期。；活动 ① 美日韩三边海上演习；② 穿越测试海区丁；③ 转赴测试陆域甲打击胡塞武装（实战）。；停靠 ：①韩国测试港城甲（3 月，约 5 天）；②测试母港F、测试港城乙樟宜（测试来源甲补充）。；天气 ：无逐次公开数据；测试海区戊 3 月早春低压/锋面，海况多变；马六甲 4 月炎热潮湿、雷雨常见。；补给 ：无逐次公开合同。；参演 1）人员：打击群司令 Amy Bauernschmidt 少将 （公开）。 2）船、飞机：测试舰CN02 CSG（CVW-T）；ROK source06、JMSDF 协同。 参演国家：测试舰艇064、韩国、日本、法国（先后）。；护航编成表 1）舰船表：①公开有限（CSG-T01 属舰）。 2）飞机表：①第2舰载机联队（CVW-T）。",
      "publishTime": "2025-03-17T00:00",
      "relatedEvent": null,
      "socialAccount": null,
      "typeCode": null,
      "catCode": "MediaReport",
      "eventTrend": null,
      "isSimulationData": null,
      "subordinateTo": null,
      "updateSeqnr": null,
      "name": "CVN-T01 测试航母11：2025 上半年 穿测试海区丁赴测试陆域甲（约 9 个月长部署收尾）",
      "publisher": null,
      "keywordTags": "CVN-T01,测试航母11,测试舰艇064航母,测试海区丁,西测试海区甲,印太部署,2020-2026,OSINT"
    },
    {
      "rawDataBlockPtr": null,
      "relatedPlatform": "CVN-T10",
      "reliability": "中高",
      "creatorId": null,
      "curStatus": null,
      "confidentialityLevel": null,
      "sourceUrl": null,
      "influenceType": null,
      "sourceOrigin": null,
      "credibilityScore": null,
      "imageUrl": "",
      "sourcePlatform": null,
      "startTime": "2026-06-15",
      "id": "00000000-0000-4000-8000-000000000000",
      "refCollectionTask": null,
      "dataUpdateTime": "2026-06-17T00:00",
      "contentSummary": "X用户Dazja Jean于2026-05-23 00:09发布“Deployment again. See you all when I get back”，印证出港当天船员动态。",
      "publishTime": "2026-05-23T00:09",
      "relatedEvent": null,
      "socialAccount": "source28",
      "typeCode": null,
      "catCode": "MediaReport",
      "eventTrend": null,
      "isSimulationData": null,
      "subordinateTo": null,
      "updateSeqnr": null,
      "name": "Dazja Jean出港当天发布部署告别帖",
      "publisher": null,
      "keywordTags": "CVN-T10,USS 测试舰,测试水面舰044,测试母港A,测试海区己,测试母港F,2026年部署,OSINT,X,船员社媒,出港当天"
    },
    {
      "rawDataBlockPtr": null,
      "relatedPlatform": "CVN-T10",
      "reliability": "中高",
      "creatorId": null,
      "curStatus": null,
      "confidentialityLevel": null,
      "sourceUrl": null,
      "influenceType": null,
      "sourceOrigin": null,
      "credibilityScore": null,
      "imageUrl": "",
      "sourcePlatform": null,
      "startTime": "2026-06-15",
      "id": "00000000-0000-4000-8000-000000000000",
      "refCollectionTask": null,
      "dataUpdateTime": "2026-06-22T00:00",
      "contentSummary": "X观察账号Warship于2026-05-17发布CVN-T10返回测试母港A的图文，显示海试结束并为正式部署做准备。",
      "publishTime": "2026-05-17T00:00",
      "relatedEvent": null,
      "socialAccount": "source29",
      "typeCode": null,
      "catCode": "MediaReport",
      "eventTrend": null,
      "isSimulationData": null,
      "subordinateTo": null,
      "updateSeqnr": null,
      "name": "Warship账号发布CVN-T10海试后返港动态",
      "publisher": null,
      "keywordTags": "CVN-T10,USS 测试舰,测试水面舰044,测试母港A,测试海区己,测试母港F,2026年部署,OSINT,X,返港,海试结束"
    },
    {
      "rawDataBlockPtr": null,
      "relatedPlatform": "CVN-T08",
      "reliability": "中高",
      "creatorId": null,
      "curStatus": null,
      "confidentialityLevel": null,
      "sourceUrl": "",
      "influenceType": null,
      "sourceOrigin": null,
      "credibilityScore": null,
      "imageUrl": null,
      "sourcePlatform": "OSINT_CARRIER_ACTIVITY_2020_2026",
      "startTime": "2026-06-15",
      "id": "00000000-0000-4000-8000-000000000000",
      "refCollectionTask": null,
      "dataUpdateTime": "2026-06-20T00:00",
      "contentSummary": "时间段 ① 2024/3/15–5/28（3/28–4/14 测试海区丁，测试来源甲口径）。 ② 2024/2 与测试舰CN02、测试舰CN09三航母同时活动于第一岛链附近。 ③ 2024/5/10/16 永久离开日本测试母港A （返美大修，由测试航母10接替前沿）。；活动 ① 美菲\"肩并肩 2024\"军演、舰载机高强度起降训练；② 三航母岛链存在展示；③ 前沿部署交接，甲板列队拼\"dewa mata（再见）\"。；停靠 ：①马尼拉港（2024/4/18–4/22，测试来源甲口径）；②测试母港A（母港，5 月离日）。；天气 ：无逐次公开数据。；补给 ：无逐次公开合同；测试母港A基地补给体系。；参演 1）人员：CSG-T10、CVW-T 人员。 2）船、飞机：测试舰CN05 CSG（CVW-T）。 参演国家：测试舰艇064、菲律宾、日本。；护航编成表 1）舰船表：①DESRON-15 属舰（公开有限）。 2）飞机表：①第5舰载机联队（CVW-T）。",
      "publishTime": "2024-03-15T00:00",
      "relatedEvent": null,
      "socialAccount": null,
      "typeCode": null,
      "catCode": "MediaReport",
      "eventTrend": null,
      "isSimulationData": null,
      "subordinateTo": null,
      "updateSeqnr": null,
      "name": "CVN-T08 测试航母07：2024/3–5 末段前沿部署与永久离日",
      "publisher": null,
      "keywordTags": "CVN-T08,测试航母07,测试舰艇064航母,测试海区丁,西测试海区甲,印太部署,2020-2026,OSINT"
    },
    {
      "rawDataBlockPtr": null,
      "relatedPlatform": "CVN-T09",
      "reliability": "中",
      "creatorId": null,
      "curStatus": null,
      "confidentialityLevel": null,
      "sourceUrl": "",
      "influenceType": null,
      "sourceOrigin": null,
      "credibilityScore": null,
      "imageUrl": null,
      "sourcePlatform": "OSINT_CARRIER_ACTIVITY_2020_2026",
      "startTime": "2026-06-15",
      "id": "00000000-0000-4000-8000-000000000000",
      "refCollectionTask": null,
      "dataUpdateTime": "2026-06-24T00:00",
      "contentSummary": "时间段 ① 2022/12/3 自测试母港B启航（部署起点）。 ② 2022/12/16 进入第七舰队责任区。 ③ 2023/1/13 进入测试海区丁（GPT 口径）；2023/1/17 本轮首次测试海区丁行动（Claude 口径）。 ④ 2023/1/26 离开测试港城乙、1/27 返回测试海区丁。 ⑤ 2023/4 月初 美日韩三边演习后，4/2 离开韩国测试港城甲。 ⑥ 2023/4/17 前后 第三次进测试海区丁，为美菲\"肩并肩\"护航。 ⑦ 2023/7/2 结束部署返航。；活动 ① 例行行动、飞行行动、海上安全行动；② 美日韩三边演习（测试海区戊）；③ 为美菲\"肩并肩 2023\"（Balikatan）护航，与测试舰艇067两栖戒备群（ USS 测试舰8/⚠️事件1.md 记 LHA-5）及第13海军陆战队远征队（13th MEU）整合远征打击演习，苏禄海活动；④ 4/22 完成第 35 万次拦阻着舰；⑤ 同期属舰测试水面舰038 DDG-T21 实施西沙/美济礁 FONOP。；停靠 ① 测试港城乙樟宜港（2023/1 下旬，物资补给与休整）。 ② 韩国测试港城甲（2023/3/27–28 抵港，4/2 离港）。 ③ ⚠️存疑：测试来源甲另记测试母港F阿普拉 4/18–4/22、马尼拉 5/15–5/19、樟宜 6/20–6/24（英文主流未对应）。；天气 ：无逐次公开数据；测试海区丁 1 月东北季风、风浪明显降雨少；5 月菲律宾外海受超强台风\"玛娃\"外围影响（测试来源甲补充）。；补给 ：无逐次公开合同；MSC 海上补给；⚠️存疑：测试来源甲记测试母港F灾后补给由\"弗莱彻集团/OSC\"（英文主流未确认承包商）。；参演 1）人员：CSG-T09 司令 Rear Adm. Christopher Sweeney （测试港城甲公开露面）；美日韩海军人员。 2）船、飞机：测试舰CN01 CSG + 护航舰；CVW-T；测试舰艇067 ARG（协同）。 参演国家：测试舰艇064、韩国、日本、菲律宾、澳大利亚（演训伙伴）。；护航编成表 1）舰船表：①测试舰CN20 CG-T01（巡洋舰）；②测试舰艇050 DDG-T36；③测试舰CN17 DDG-T62；④韦恩·E·迈耶 DDG-T14（DESRON-9）。 2）飞机表：①第17舰载机联队（CVW-T）所属各中队。",
      "publishTime": "2022-12-03T00:00",
      "relatedEvent": null,
      "socialAccount": null,
      "typeCode": null,
      "catCode": "MediaReport",
      "eventTrend": null,
      "isSimulationData": null,
      "subordinateTo": null,
      "updateSeqnr": null,
      "name": "CVN-T09 测试航母03：2022/12–2023/7 印太部署（CSG-T09 / CVW-T）",
      "publisher": null,
      "keywordTags": "CVN-T09,测试航母03,测试舰艇064航母,测试海区丁,西测试海区甲,印太部署,2020-2026,OSINT"
    },
    {
      "rawDataBlockPtr": null,
      "relatedPlatform": "CVN-T10",
      "reliability": "中高",
      "creatorId": null,
      "curStatus": null,
      "confidentialityLevel": null,
      "sourceUrl": null,
      "influenceType": null,
      "sourceOrigin": null,
      "credibilityScore": null,
      "imageUrl": "",
      "sourcePlatform": null,
      "startTime": "2026-06-15",
      "id": "00000000-0000-4000-8000-000000000000",
      "refCollectionTask": null,
      "dataUpdateTime": "2026-06-16T00:00",
      "contentSummary": "X用户Jasmine V于2026-05-09发布即将离开执行最后一次部署的信息，并公开CVN-T10通信地址，构成出港预警。",
      "publishTime": "2026-05-09T00:00",
      "relatedEvent": null,
      "socialAccount": "source30",
      "typeCode": null,
      "catCode": "MediaReport",
      "eventTrend": null,
      "isSimulationData": null,
      "subordinateTo": null,
      "updateSeqnr": null,
      "name": "Jasmine V发布“最后一次部署”告别帖",
      "publisher": null,
      "keywordTags": "CVN-T10,USS 测试舰,测试水面舰044,测试母港A,测试海区己,测试母港F,2026年部署,OSINT,X,部署预警,船员社媒"
    },
    {
      "rawDataBlockPtr": null,
      "relatedPlatform": "CVN-T10",
      "reliability": "中高",
      "creatorId": null,
      "curStatus": null,
      "confidentialityLevel": null,
      "sourceUrl": null,
      "influenceType": null,
      "sourceOrigin": null,
      "credibilityScore": null,
      "imageUrl": "",
      "sourcePlatform": "ADSB_TRACKER",
      "startTime": "2026-06-20",
      "id": "00000000-0000-4000-8000-000000000000",
      "refCollectionTask": null,
      "dataUpdateTime": "2026-06-26T00:00",
      "contentSummary": "AEEBA3在测试海区己/四国外海方向活动，航迹和SAR底图共同用于反推航母训练区域。",
      "publishTime": "2026-05-30T21:00",
      "relatedEvent": null,
      "socialAccount": null,
      "typeCode": null,
      "catCode": "MediaReport",
      "eventTrend": null,
      "isSimulationData": null,
      "subordinateTo": null,
      "updateSeqnr": null,
      "name": "AEEBA3航迹与SAR卫星图",
      "publisher": null,
      "keywordTags": "CVN-T10,USS 测试舰,测试水面舰044,测试母港A,测试海区己,测试母港F,2026年部署,OSINT,ADS-B,AEEBA3,SAR"
    },
    {
      "rawDataBlockPtr": null,
      "relatedPlatform": "CVN-T01",
      "reliability": "中高",
      "creatorId": null,
      "curStatus": null,
      "confidentialityLevel": null,
      "sourceUrl": "",
      "influenceType": null,
      "sourceOrigin": null,
      "credibilityScore": null,
      "imageUrl": null,
      "sourcePlatform": "OSINT_CARRIER_ACTIVITY_2020_2026",
      "startTime": "2026-06-15",
      "id": "00000000-0000-4000-8000-000000000000",
      "refCollectionTask": null,
      "dataUpdateTime": "2026-06-22T00:00",
      "contentSummary": "时间段 ① 2024 年夏季（测试陆地甲海域），演习后返测试母港B维护。；活动 ：① 环测试海区甲-2024（RIMPAC）多国大型演习。；停靠 ：①测试陆地甲（测试母港E-希卡姆基地，演习驻泊）。；天气 ：无逐次公开数据。；补给 ：无逐次公开合同；演习依托基地与 MSC 体系。；参演 1）人员：CSG-T01 舰员。 2）船、飞机：测试舰CN02 CSG（CVW-T）。 参演国家：测试舰艇064及数十国。；护航编成表 1）舰船表：①公开有限。 2）飞机表：①第2舰载机联队（CVW-T）。",
      "publishTime": "2024-01-01T00:00",
      "relatedEvent": null,
      "socialAccount": null,
      "typeCode": null,
      "catCode": "MediaReport",
      "eventTrend": null,
      "isSimulationData": null,
      "subordinateTo": null,
      "updateSeqnr": null,
      "name": "CVN-T01 测试航母11：2024 RIMPAC（环测试海区甲-2024）",
      "publisher": null,
      "keywordTags": "CVN-T01,测试航母11,测试舰艇064航母,测试海区丁,西测试海区甲,印太部署,2020-2026,OSINT"
    },
    {
      "rawDataBlockPtr": null,
      "relatedPlatform": null,
      "reliability": null,
      "creatorId": "OSINT_analyst02",
      "curStatus": "PUBLISHED",
      "confidentialityLevel": null,
      "sourceUrl": "",
      "influenceType": "POSITIVE",
      "sourceOrigin": null,
      "credibilityScore": "0.98",
      "imageUrl": null,
      "sourcePlatform": "新闻报道",
      "startTime": null,
      "id": "NR_20260226_003",
      "refCollectionTask": null,
      "dataUpdateTime": "2026-06-14T00:00",
      "contentSummary": "路透社特约记者现场报道，美伊双方在2月26日的和谈中，就核不扩散、制裁放宽议题达成初步框架共识",
      "publishTime": "2026-02-26T11:15",
      "relatedEvent": "US_IRAN_PEACE_TALKS",
      "socialAccount": null,
      "typeCode": "NEWS_REPORT",
      "catCode": "MediaReport",
      "eventTrend": "局势缓和",
      "isSimulationData": "1",
      "subordinateTo": "路透社",
      "updateSeqnr": "SEQ_003",
      "name": "路透社报道美伊和谈达成初步共识",
      "publisher": null,
      "keywordTags": "美伊和谈,初步共识,核不扩散"
    },
    {
      "rawDataBlockPtr": null,
      "relatedPlatform": null,
      "reliability": null,
      "creatorId": null,
      "curStatus": "PUBLISHED",
      "confidentialityLevel": null,
      "sourceUrl": "",
      "influenceType": "POSITIVE",
      "sourceOrigin": null,
      "credibilityScore": null,
      "imageUrl": null,
      "sourcePlatform": "NAVY_MIL",
      "startTime": null,
      "id": "OSINT_NICHOLAS_DELEO_003",
      "refCollectionTask": null,
      "dataUpdateTime": "2026-06-23T00:00",
      "contentSummary": "表示为能够成为蓝岭号指挥团队一员而感到自豪，感谢舰员及指挥部在任期内共同完成任务。",
      "publishTime": "2025-09-05T00:00",
      "relatedEvent": null,
      "socialAccount": null,
      "typeCode": null,
      "catCode": "MediaReport",
      "eventTrend": null,
      "isSimulationData": null,
      "subordinateTo": null,
      "updateSeqnr": null,
      "name": "卸任蓝岭号测试员147感谢官兵",
      "publisher": "source24",
      "keywordTags": "蓝岭号,第七舰队,测试员147交接,舰员,领导力"
    },
    {
      "rawDataBlockPtr": null,
      "relatedPlatform": null,
      "reliability": null,
      "creatorId": "OSINT_analyst02",
      "curStatus": "PUBLISHED",
      "confidentialityLevel": null,
      "sourceUrl": "",
      "influenceType": "POSITIVE",
      "sourceOrigin": null,
      "credibilityScore": "0.99",
      "imageUrl": null,
      "sourcePlatform": "官方网站",
      "startTime": null,
      "id": "OSW_20260225_001",
      "refCollectionTask": null,
      "dataUpdateTime": "2026-06-22T00:00",
      "contentSummary": "测试陆域丙外交部官方网站正式发布声明，宣布与测试舰艇064启动新一轮闭门和谈，核心围绕核协议、测试陆域甲安全框架展开磋商",
      "publishTime": "2026-02-25T09:00",
      "relatedEvent": "US_IRAN_PEACE_TALKS",
      "socialAccount": null,
      "typeCode": "OFFICIAL_NEWS",
      "catCode": "MediaReport",
      "eventTrend": "局势缓和",
      "isSimulationData": "1",
      "subordinateTo": "测试陆域丙政府",
      "updateSeqnr": "SEQ_001",
      "name": "测试陆域丙外交部官网发布美伊和谈启动公告",
      "publisher": null,
      "keywordTags": "美伊和谈,测试陆域丙外交部,核协议"
    },
    {
      "rawDataBlockPtr": null,
      "relatedPlatform": "CVN-T01",
      "reliability": "中",
      "creatorId": null,
      "curStatus": null,
      "confidentialityLevel": null,
      "sourceUrl": "",
      "influenceType": null,
      "sourceOrigin": null,
      "credibilityScore": null,
      "imageUrl": null,
      "sourcePlatform": "OSINT_CARRIER_ACTIVITY_2020_2026",
      "startTime": "2026-06-15",
      "id": "00000000-0000-4000-8000-000000000000",
      "refCollectionTask": null,
      "dataUpdateTime": "2026-06-15T00:00",
      "contentSummary": "时间段 ① 2024/12/23 入测试海区丁。 ② 2024/12/26 前后 测试海区丁飞行行动（测试港城乙停靠背景）。 ③ 2025/1/17–1/18 美菲海上军演。 ④ 2025/2/6 经苏禄海驶离测试海区丁（本阶段测试海区丁约 45 天）。 ⑤ 2025/2/8–2/18 测试海区己（约 15–20°N,130–140°E）参加\"测试海区甲斯特勒 2025\"（测试海区甲 Steller）美法日三航母演习。；活动 ① 美菲巴拉望海上合作演习；② \"测试海区甲斯特勒 2025\"三航母演习——与法\"测试航母08\"R91、日\"加贺\"DDH-184 编队，开展反潜、空中防御、跨甲板作业及多域协调，提升三国互操作性；③ 港口外事访问。；停靠 ：①马来西亚巴生港（2024/12/29–2025/1/2）；②泰国林查班港（2025/1/27–1/31）。（测试来源甲口径）；天气 ：无逐次公开数据；12–1 月测试海区丁东北季风、海面多风浪，无台风。；补给 ：无逐次公开合同；⚠️测试来源甲记巴生港 BP 马来西亚供油、林查班泰国国家石油+OSC 干货补给（英文主流未确认）。；参演 1）人员：⚠️存疑\"CSG-T01 指挥官丹·马丁少将\"（仅测试来源甲）。 2）船、飞机：测试舰CN02 CSG（CVW-T），护航测试舰CN14 CG-T04、测试水面舰025 DDG-T25、威廉·P·劳伦斯 DDG-T31；法\"测试航母08\"R91；日\"加贺\"DDH-184、\"测试舰CN46\"DD-T04 等。 参演国家：测试舰艇064、菲律宾、日本、法国。；护航编成表 1）舰船表：①公开有限。 2）飞机表：①第2舰载机联队（CVW-T）。",
      "publishTime": "2024-12-23T00:00",
      "relatedEvent": null,
      "socialAccount": null,
      "typeCode": null,
      "catCode": "MediaReport",
      "eventTrend": null,
      "isSimulationData": null,
      "subordinateTo": null,
      "updateSeqnr": null,
      "name": "CVN-T01 测试航母11：2024/12–2025/2 跨年度测试海区丁部署",
      "publisher": null,
      "keywordTags": "CVN-T01,测试航母11,测试舰艇064航母,测试海区丁,西测试海区甲,印太部署,2020-2026,OSINT"
    },
    {
      "rawDataBlockPtr": null,
      "relatedPlatform": "CVN-T10",
      "reliability": "中高",
      "creatorId": null,
      "curStatus": null,
      "confidentialityLevel": null,
      "sourceUrl": null,
      "influenceType": null,
      "sourceOrigin": null,
      "credibilityScore": null,
      "imageUrl": "",
      "sourcePlatform": "AIS_TRACKER",
      "startTime": "2026-06-15",
      "id": "00000000-0000-4000-8000-000000000000",
      "refCollectionTask": null,
      "dataUpdateTime": "2026-06-15T00:00",
      "contentSummary": "AIS显示CG-T02于2026-05-23至05-25从东京湾/测试母港A外海向西南机动，至132.26E/31.11N附近，填补航母编队西行空窗。",
      "publishTime": "2026-05-25T07:16",
      "relatedEvent": null,
      "socialAccount": null,
      "typeCode": null,
      "catCode": "MediaReport",
      "eventTrend": null,
      "isSimulationData": null,
      "subordinateTo": null,
      "updateSeqnr": null,
      "name": "CG-T02罗伯特·史莫斯号出港后向西南机动AIS航迹",
      "publisher": null,
      "keywordTags": "CVN-T10,USS 测试舰,测试水面舰044,测试母港A,测试海区己,测试母港F,2026年部署,OSINT,AIS,CG-T02,护航舰"
    },
    {
      "rawDataBlockPtr": null,
      "relatedPlatform": "CVN-T10",
      "reliability": "中",
      "creatorId": null,
      "curStatus": null,
      "confidentialityLevel": null,
      "sourceUrl": null,
      "influenceType": null,
      "sourceOrigin": null,
      "credibilityScore": null,
      "imageUrl": "",
      "sourcePlatform": "SATELLITE_IMAGERY",
      "startTime": "2026-06-15",
      "id": "00000000-0000-4000-8000-000000000000",
      "refCollectionTask": null,
      "dataUpdateTime": "2026-06-22T00:00",
      "contentSummary": "综合2025年测试母港F周边公开活动，标注阿普拉港、测试母港F东西侧海域、北侧空域和南侧进近通道等活动规律。",
      "publishTime": "2025-08-28T00:00",
      "relatedEvent": null,
      "socialAccount": null,
      "typeCode": null,
      "catCode": "MediaReport",
      "eventTrend": null,
      "isSimulationData": null,
      "subordinateTo": null,
      "updateSeqnr": null,
      "name": "CVN-T10测试母港F周边历史活动分布态势图",
      "publisher": null,
      "keywordTags": "CVN-T10,USS 测试舰,测试水面舰044,测试母港A,测试海区己,测试母港F,2026年部署,OSINT,测试母港F,历史活动,态势图"
    },
    {
      "rawDataBlockPtr": null,
      "relatedPlatform": "CVN-T10",
      "reliability": "中高",
      "creatorId": null,
      "curStatus": null,
      "confidentialityLevel": null,
      "sourceUrl": "",
      "influenceType": null,
      "sourceOrigin": null,
      "credibilityScore": null,
      "imageUrl": null,
      "sourcePlatform": "OSINT_CARRIER_ACTIVITY_2020_2026",
      "startTime": "2026-06-15",
      "id": "00000000-0000-4000-8000-000000000000",
      "refCollectionTask": null,
      "dataUpdateTime": "2026-06-14T00:00",
      "contentSummary": "时间段 ① 2025/6/10 左右 自测试母港A启航， 首次前沿巡航 ，数日内抵测试海区己核心区（约 15°N,130°E）。 ② 2025/6/28 海上加油（公开照片）。 ③ 2025/7/3 抵马尼拉（首次访菲），7/7 离港线索；7/2 在测试海区丁开展飞行作业并接待菲律宾媒体参观。 ④ 2025/7/14–7 下旬 护身军刀 2025（Talisman Sabre），帝汶海/测试海区己。 ⑤ 2025/8–9 月 测试海区己飞行作业与例行巡逻，后短暂休整。 ⑥ 2025/9/30 休整后 重启巡航 （测试海区己，飞行作业与例行巡逻）。 ⑦ 2025/11/12 与韩国海军 CSGEX 2025 联合演习（测试海区己/韩国附近）。 ⑧ 2025/11/17–22 经吕宋海峡进入测试海区丁（约 12°N,114°E），支持附近行动、飞行作业与存在展示 → 12/5 驶出测试海区丁（本阶段测试海区丁驻留约 19 天），与测试舰CN01 CSG 短暂会合（10/17 起）。；活动 ① 首次前沿部署巡逻；② 护身军刀 2025（返前沿后首次重大多国演习，英\"威尔士亲王\"R09 双航母演习）；③ 测试海区己三航母+6 国多国训练（含日\"加贺\"DDH-184）、美日韩弗里德姆刀锋；④ 美菲近海协同、舰载联队资质认证训练；⑤ 美韩 CSGEX 2025 海上编队与空中协同；⑥ 经吕宋海峡入测试海区丁巡逻，期间曾访测试母港F、韩国、菲律宾、参加多边演习。；停靠 ：①菲律宾马尼拉港（7/3–7/7，首次访菲）；②测试母港A母港（约 10 月休整）；③测试母港F、韩国、菲律宾（11 月前后公开线索）。；天气 ：无逐次公开数据；马尼拉 7 月雨季湿热多雷雨；测试海区己/测试海区丁常态热带海洋；11 月测试海区丁东北季风初期、风浪增强。；补给 ： 公开照片 显示 2025/6/28 在测试海区己与油轮 Allied 测试海区甲 进行海上加油；商业合同细节未公开。；参演 1）人员：CSG-T10、CVW-T、第七舰队前沿部署人员；菲律宾接待方；韩国海军（CSGEX）。 2）船、飞机：测试航母10 CSG（CVW-T）；护航 罗伯特·斯莫斯 CG-T02、舒普 DDG-T05、测试水面舰038 DDG-T21 ；护身军刀含英\"威尔士亲王\"R09；测试海区己训练含日\"加贺\"DDH-184 等多国舰艇。 参演国家：测试舰艇064、日本、韩国、菲律宾、澳大利亚、英国。；护航编成表 1）舰船表：①罗伯特·斯莫斯 CG-T02（巡洋舰）；②舒普 DDG-T05；③测试水面舰038 DDG-T21（DESRON-15）。 2）飞机表：①第5舰载机联队（CVW-T）。",
      "publishTime": "2025-06-10T00:00",
      "relatedEvent": null,
      "socialAccount": null,
      "typeCode": null,
      "catCode": "MediaReport",
      "eventTrend": null,
      "isSimulationData": null,
      "subordinateTo": null,
      "updateSeqnr": null,
      "name": "CVN-T10 测试水面舰044：2025/6–2025/11 首次前沿巡航（马尼拉、护身军刀、CSGEX、测试海区丁）",
      "publisher": null,
      "keywordTags": "CVN-T10,测试水面舰044,测试舰艇064航母,测试海区丁,西测试海区甲,印太部署,2020-2026,OSINT"
    },
    {
      "rawDataBlockPtr": null,
      "relatedPlatform": "CVN-T10",
      "reliability": "中高",
      "creatorId": null,
      "curStatus": null,
      "confidentialityLevel": null,
      "sourceUrl": null,
      "influenceType": null,
      "sourceOrigin": null,
      "credibilityScore": null,
      "imageUrl": "",
      "sourcePlatform": "SATELLITE_IMAGERY",
      "startTime": "2026-06-15",
      "id": "00000000-0000-4000-8000-000000000000",
      "refCollectionTask": null,
      "dataUpdateTime": "2026-06-14T00:00",
      "contentSummary": "卫星影像显示CVN-T10短暂离港，结合后文判断为海试/训练窗口。",
      "publishTime": "2026-05-14T00:00",
      "relatedEvent": null,
      "socialAccount": null,
      "typeCode": null,
      "catCode": "MediaReport",
      "eventTrend": null,
      "isSimulationData": null,
      "subordinateTo": null,
      "updateSeqnr": null,
      "name": "2026-05-14 测试母港A12号码头卫星图显示CVN-T10不在港",
      "publisher": null,
      "keywordTags": "CVN-T10,USS 测试舰,测试水面舰044,测试母港A,测试海区己,测试母港F,2026年部署,OSINT,卫星影像,海试"
    },
    {
      "rawDataBlockPtr": null,
      "relatedPlatform": "CVN-T10",
      "reliability": "中高",
      "creatorId": null,
      "curStatus": null,
      "confidentialityLevel": null,
      "sourceUrl": null,
      "influenceType": null,
      "sourceOrigin": null,
      "credibilityScore": null,
      "imageUrl": "",
      "sourcePlatform": "SATELLITE_IMAGERY",
      "startTime": "2026-06-15",
      "id": "00000000-0000-4000-8000-000000000000",
      "refCollectionTask": null,
      "dataUpdateTime": "2026-06-14T00:00",
      "contentSummary": "卫星影像显示CVN-T10返回并停靠测试母港A12号码头，印证2025年12月返港状态。",
      "publishTime": "2025-12-12T00:00",
      "relatedEvent": null,
      "socialAccount": null,
      "typeCode": null,
      "catCode": "MediaReport",
      "eventTrend": null,
      "isSimulationData": null,
      "subordinateTo": null,
      "updateSeqnr": null,
      "name": "2025-12-12 测试母港A12号码头卫星图显示CVN-T10在港",
      "publisher": null,
      "keywordTags": "CVN-T10,USS 测试舰,测试水面舰044,测试母港A,测试海区己,测试母港F,2026年部署,OSINT,卫星影像,在港基线"
    },
    {
      "rawDataBlockPtr": null,
      "relatedPlatform": "CVN-T10",
      "reliability": "中高",
      "creatorId": null,
      "curStatus": null,
      "confidentialityLevel": null,
      "sourceUrl": null,
      "influenceType": null,
      "sourceOrigin": null,
      "credibilityScore": null,
      "imageUrl": "",
      "sourcePlatform": "ADSB_TRACKER",
      "startTime": "2026-06-15",
      "id": "00000000-0000-4000-8000-000000000000",
      "refCollectionTask": null,
      "dataUpdateTime": "2026-06-24T00:00",
      "contentSummary": "两架V-22在CVN-T10认证训练区域外围往返机动，活动中心指向航母大致位置。",
      "publishTime": "2026-05-30T21:18",
      "relatedEvent": null,
      "socialAccount": null,
      "typeCode": null,
      "catCode": "MediaReport",
      "eventTrend": null,
      "isSimulationData": null,
      "subordinateTo": null,
      "updateSeqnr": null,
      "name": "AE6BAD/AEEBA3与CVN-T10关联态势图",
      "publisher": null,
      "keywordTags": "CVN-T10,USS 测试舰,测试水面舰044,测试母港A,测试海区己,测试母港F,2026年部署,OSINT,ADS-B,V-22,关联态势"
    },
    {
      "rawDataBlockPtr": null,
      "relatedPlatform": "CVN-T10",
      "reliability": "中高",
      "creatorId": null,
      "curStatus": null,
      "confidentialityLevel": null,
      "sourceUrl": null,
      "influenceType": null,
      "sourceOrigin": null,
      "credibilityScore": null,
      "imageUrl": "",
      "sourcePlatform": null,
      "startTime": "2026-06-15",
      "id": "00000000-0000-4000-8000-000000000000",
      "refCollectionTask": null,
      "dataUpdateTime": "2026-06-14T00:00",
      "contentSummary": "X观察账号Warship于2026-05-10发布测试水面舰044离开测试母港A的实拍组图。",
      "publishTime": "2026-05-10T00:00",
      "relatedEvent": null,
      "socialAccount": "source29",
      "typeCode": null,
      "catCode": "MediaReport",
      "eventTrend": null,
      "isSimulationData": null,
      "subordinateTo": null,
      "updateSeqnr": null,
      "name": "Warship账号发布CVN-T10海试离港实景",
      "publisher": null,
      "keywordTags": "CVN-T10,USS 测试舰,测试水面舰044,测试母港A,测试海区己,测试母港F,2026年部署,OSINT,X,海试,实景照片"
    },
    {
      "rawDataBlockPtr": null,
      "relatedPlatform": "CVN-T05",
      "reliability": "中高",
      "creatorId": null,
      "curStatus": null,
      "confidentialityLevel": null,
      "sourceUrl": "",
      "influenceType": null,
      "sourceOrigin": null,
      "credibilityScore": null,
      "imageUrl": null,
      "sourcePlatform": "OSINT_CARRIER_ACTIVITY_2020_2026",
      "startTime": "2026-06-15",
      "id": "00000000-0000-4000-8000-000000000000",
      "refCollectionTask": null,
      "dataUpdateTime": "2026-06-18T00:00",
      "contentSummary": "时间段 ① 2024/1 启航部署（测试母港B）。 ② 2024/2/6 起 测试母港F海军基地港访。 ③ 2024/2 与测试舰CN05、测试舰CN02三航母同时活动于第一岛链附近。 ④ 2024/4/24–4/28 泰国林查班港访。 ⑤ 2024/5/7–5/10 美菲\"肩并肩 2024\"（Balikatan）期间在演习区附近。 ⑥ 2024/4/18–6/13 测试海区丁长时间作业（约 58 天，含 5/26–6/11 穿越测试海区丁），6/11 海上补给照片公开；另 3/1–4/1 经巴士/巴拉巴克海峡进测试海区丁，7/3–7、9/17–20 多次短时测试海区丁作业（事件1.md 口径）。 ⑦ 2024/6/7–6/18 勇敢之盾 2024（Valiant Shield）。 ⑧ 2024/6/22–6/26 测试港城甲港访（为弗里德姆刀锋做准备）。 ⑨ 2024/6/27–6/29 弗里德姆刀锋（Freedom Edge）首次三边演习。 ⑩ 2024/9/11 离测试陆域甲返测试海区甲（部署约 8 个月）；9/26 前后 测试母港F港访。；活动 ① 测试母港F后勤休整；② 三航母岛链存在展示；③ 林查班伙伴交流；④ Balikatan 周边活动（未直接参演）；⑤ 例行/飞行行动与海上补给；⑥ 勇敢之盾 2024 多域演习（编队航行、飞越、实弹/沉船演练，与法、加护卫舰编队航行，万安滩附近）；⑦ 弗里德姆刀锋首次美日韩三边多域演习。；停靠 ：①测试母港F海军基地（2/6 起；9/26 前后）；②泰国林查班港（4/24–4/28）；③韩国测试港城甲（6/22–6/26）。；天气 ：无逐次公开数据；测试母港F 2 月相对干季、9 月雨季/台风季；林查班 4 月热季高温高湿；测试港城甲 6 月梅雨季前后湿度升高；测试海区丁 5–6 月雨季/台风季。；补给 ：无逐次公开合同；2024/6/11 公开照片显示与 USS 测试舰 (DDG-T32) 进行海上补给相关活动（属舰间补给/伴随保障影像，非完整补给计划）；本部署关联补给油船 USNS 测试舰（T-AO-194） （事件1.md）；港口后勤由美军基地/MSC 体系支援。；参演 1）人员：CSG-T05、CVW-T、DESRON-23 人员；测试港城甲港访期间 韩国总统尹锡悦登舰/讲话线索 （韩媒+USNI 转述）。 2）船、飞机：测试舰CN09 CSG；测试港城甲期间含 USS 测试舰 、 USS 测试舰 ；勇敢之盾含 USS 测试舰 （第七舰队旗舰）等；CVW-T。 参演国家：测试舰艇064、日本、韩国、菲律宾、法国、加拿大（勇敢之盾）。；护航编成表 1）舰船表：①伊利湖 CG-T14（巡洋舰）；②约翰·S·测试舰CN22 DDG；③拉塞尔 DDG-T38；④测试舰CN29 DDG-T01；⑤测试舰CN26 DDG-T02（DESRON-23）；⑥莱特湾 CG（启航护航，公开提及）。 2）飞机表：①第11舰载机联队（CVW-T）所属各中队。",
      "publishTime": "2024-02-06T00:00",
      "relatedEvent": null,
      "socialAccount": null,
      "typeCode": null,
      "catCode": "MediaReport",
      "eventTrend": null,
      "isSimulationData": null,
      "subordinateTo": null,
      "updateSeqnr": null,
      "name": "CVN-T05 测试航母09：2024/1–2024/10 约 8 个月部署（CSG-T05 / CVW-T）",
      "publisher": null,
      "keywordTags": "CVN-T05,测试航母09,测试舰艇064航母,测试海区丁,西测试海区甲,印太部署,2020-2026,OSINT"
    },
    {
      "rawDataBlockPtr": null,
      "relatedPlatform": "CVN-T10",
      "reliability": "中高",
      "creatorId": null,
      "curStatus": null,
      "confidentialityLevel": null,
      "sourceUrl": null,
      "influenceType": null,
      "sourceOrigin": null,
      "credibilityScore": null,
      "imageUrl": "",
      "sourcePlatform": "AIS_TRACKER",
      "startTime": "2026-06-15",
      "id": "00000000-0000-4000-8000-000000000000",
      "refCollectionTask": null,
      "dataUpdateTime": "2026-06-20T00:00",
      "contentSummary": "AIS航次信息显示TANKER 207/USNS 测试舰（IMO IMO_TEST_00001，MMSI 999000026）从测试母港A驶往测试母港F，实际离港2026-05-27，预计2026-06-03抵达。",
      "publishTime": "2026-05-27T06:16",
      "relatedEvent": null,
      "socialAccount": null,
      "typeCode": null,
      "catCode": "MediaReport",
      "eventTrend": null,
      "isSimulationData": null,
      "subordinateTo": null,
      "updateSeqnr": null,
      "name": "T-AO-207测试母港A至测试母港FAIS航次信息",
      "publisher": null,
      "keywordTags": "CVN-T10,USS 测试舰,测试水面舰044,测试母港A,测试海区己,测试母港F,2026年部署,OSINT,AIS,T-AO-207,测试母港F"
    },
    {
      "rawDataBlockPtr": null,
      "relatedPlatform": "CVN-T10",
      "reliability": "中高",
      "creatorId": null,
      "curStatus": null,
      "confidentialityLevel": null,
      "sourceUrl": null,
      "influenceType": null,
      "sourceOrigin": null,
      "credibilityScore": null,
      "imageUrl": "",
      "sourcePlatform": "ADSB_TRACKER",
      "startTime": "2026-06-23",
      "id": "00000000-0000-4000-8000-000000000000",
      "refCollectionTask": null,
      "dataUpdateTime": "2026-06-25T00:00",
      "contentSummary": "AE6BAD（V-22/注册号169460）与AEEBA3同批次在测试海区己方向活动，构成伴飞机关联证据。",
      "publishTime": "2026-05-30T21:00",
      "relatedEvent": null,
      "socialAccount": null,
      "typeCode": null,
      "catCode": "MediaReport",
      "eventTrend": null,
      "isSimulationData": null,
      "subordinateTo": null,
      "updateSeqnr": null,
      "name": "AE6BAD V-22航迹截图",
      "publisher": null,
      "keywordTags": "CVN-T10,USS 测试舰,测试水面舰044,测试母港A,测试海区己,测试母港F,2026年部署,OSINT,ADS-B,AE6BAD,V-22"
    },
    {
      "rawDataBlockPtr": null,
      "relatedPlatform": "CVN-T10",
      "reliability": "中高",
      "creatorId": null,
      "curStatus": null,
      "confidentialityLevel": null,
      "sourceUrl": null,
      "influenceType": null,
      "sourceOrigin": null,
      "credibilityScore": null,
      "imageUrl": "",
      "sourcePlatform": "ADSB_TRACKER",
      "startTime": "2026-06-15",
      "id": "00000000-0000-4000-8000-000000000000",
      "refCollectionTask": null,
      "dataUpdateTime": "2026-06-22T00:00",
      "contentSummary": "AEEBA3自2026-05-30 15时至2026-06-03 07时沿四国南侧外海往返，符合航母资格训练阶段固定海域作业特征。",
      "publishTime": "2026-06-03T07:00",
      "relatedEvent": null,
      "socialAccount": null,
      "typeCode": null,
      "catCode": "MediaReport",
      "eventTrend": null,
      "isSimulationData": null,
      "subordinateTo": null,
      "updateSeqnr": null,
      "name": "AEEBA3四国外海至测试海区己完整训练航迹",
      "publisher": null,
      "keywordTags": "CVN-T10,USS 测试舰,测试水面舰044,测试母港A,测试海区己,测试母港F,2026年部署,OSINT,ADS-B,AEEBA3,训练航迹"
    },
    {
      "rawDataBlockPtr": null,
      "relatedPlatform": "CVN-T10",
      "reliability": "中高",
      "creatorId": null,
      "curStatus": null,
      "confidentialityLevel": null,
      "sourceUrl": null,
      "influenceType": null,
      "sourceOrigin": null,
      "credibilityScore": null,
      "imageUrl": "",
      "sourcePlatform": null,
      "startTime": "2026-06-15",
      "id": "00000000-0000-4000-8000-000000000000",
      "refCollectionTask": null,
      "dataUpdateTime": "2026-06-21T00:00",
      "contentSummary": "X用户Bradley Bau于2026-04-01发布“Argos out in 测试母港F”及GUAM DETACHMENT 2026配图，指向VFA-147在测试母港F分遣训练。",
      "publishTime": "2026-04-01T00:00",
      "relatedEvent": null,
      "socialAccount": "source31",
      "typeCode": null,
      "catCode": "MediaReport",
      "eventTrend": null,
      "isSimulationData": null,
      "subordinateTo": null,
      "updateSeqnr": null,
      "name": "Bradley Bau发布VFA-147测试母港F分遣训练动态",
      "publisher": null,
      "keywordTags": "CVN-T10,USS 测试舰,测试水面舰044,测试母港A,测试海区己,测试母港F,2026年部署,OSINT,X,VFA-147,测试母港F分遣"
    },
    {
      "rawDataBlockPtr": null,
      "relatedPlatform": "CVN-T02",
      "reliability": "中",
      "creatorId": null,
      "curStatus": null,
      "confidentialityLevel": null,
      "sourceUrl": "",
      "influenceType": null,
      "sourceOrigin": null,
      "credibilityScore": null,
      "imageUrl": null,
      "sourcePlatform": "OSINT_CARRIER_ACTIVITY_2020_2026",
      "startTime": "2026-06-15",
      "id": "00000000-0000-4000-8000-000000000000",
      "refCollectionTask": null,
      "dataUpdateTime": "2026-06-23T00:00",
      "contentSummary": "时间段 ① 2023/12/2–12/28（测试海区己+巴士海峡，短暂入测试海区丁约 3 天）。⚠️存疑：该次主要见测试来源甲稿，英文主流对应有限。；活动 ：① 年终编队整训、跨海峡机动演练。；停靠 ：①测试母港F阿普拉（12/15–12/19）。；天气 ：无逐次公开数据。；补给 ：无逐次公开合同。；参演 1）人员：CSG-T02 人员（普通名单不公开）。 2）船、飞机：测试舰CN37 CSG（CVW-T）。 参演国家：测试舰艇064。；护航编成表 1）舰船表：①公开有限。 2）飞机表：①第9舰载机联队（CVW-T）。",
      "publishTime": "2023-12-02T00:00",
      "relatedEvent": null,
      "socialAccount": null,
      "typeCode": null,
      "catCode": "MediaReport",
      "eventTrend": null,
      "isSimulationData": null,
      "subordinateTo": null,
      "updateSeqnr": null,
      "name": "CVN-T02 测试航母12：2023/12 测试海区己—巴士海峡整训（短暂入测试海区丁）",
      "publisher": null,
      "keywordTags": "CVN-T02,测试航母12,测试舰艇064航母,测试海区丁,西测试海区甲,印太部署,2020-2026,OSINT"
    },
    {
      "rawDataBlockPtr": null,
      "relatedPlatform": "CVN-T01",
      "reliability": "中",
      "creatorId": null,
      "curStatus": null,
      "confidentialityLevel": null,
      "sourceUrl": "",
      "influenceType": null,
      "sourceOrigin": null,
      "credibilityScore": null,
      "imageUrl": null,
      "sourcePlatform": "OSINT_CARRIER_ACTIVITY_2020_2026",
      "startTime": "2026-06-15",
      "id": "00000000-0000-4000-8000-000000000000",
      "refCollectionTask": null,
      "dataUpdateTime": "2026-06-18T00:00",
      "contentSummary": "时间段 ① 2021/8/2 启航部署（CVW-T，VFA-147 携 F-35C）。 ② 2021/9/9 本部署首次进入测试海区丁（GPT 口径）；测试来源甲记测试海区丁驻留 10/12–10/28（约 17 天）。 ③ 2021/10/25–11 上旬 与测试海区庚自印太部署编队活动。 ④ 2021/12/30 部署收尾（续至 2022/2）。；活动 ① LSE2021 大规模演习、美英航母联合演训、美日双边军演、战备巡航；② 飞行行动、海上打击演练、空面协同战术训练（F-35C 首次随航母作战部署背景）。；停靠 ① 测试母港F阿普拉（9/1–9/5）；②测试港城乙樟宜（11/2–11/7）；③泰国林查班（12/20–12/25）。（测试来源甲口径）；天气 ：无逐次公开数据；10 月测试海区丁秋台外围环流、局部暴雨；测试港城乙雨季阵雨。；补给 ：无逐次公开合同；⚠️测试来源甲记 OSC+MSC 分段补给、测试港城乙樟宜由壳牌海事代理供货（英文主流未确认承包商）。；参演 1）人员：CSG-T01 指挥官 ⚠️存疑\"丹·马丁少将\"（仅测试来源甲）。 2）船、飞机：测试舰CN02 CSG；CVW-T 含 VFA-147（F-35C）。 参演国家：测试舰艇064、英国（伊丽莎白女王号编队）、日本、测试港城乙、泰国。；护航编成表 1）舰船表：①公开有限（护航驱逐舰多艘，番号未系统披露）。 2）飞机表：①第2舰载机联队（CVW-T），含 VFA-147（F-35C）。",
      "publishTime": "2021-08-02T00:00",
      "relatedEvent": null,
      "socialAccount": null,
      "typeCode": null,
      "catCode": "MediaReport",
      "eventTrend": null,
      "isSimulationData": null,
      "subordinateTo": null,
      "updateSeqnr": null,
      "name": "CVN-T01 测试航母11：2021/8–2021/12 首次 F-35C 作战部署",
      "publisher": null,
      "keywordTags": "CVN-T01,测试航母11,测试舰艇064航母,测试海区丁,西测试海区甲,印太部署,2020-2026,OSINT"
    },
    {
      "rawDataBlockPtr": null,
      "relatedPlatform": "CVN-T10",
      "reliability": "中高",
      "creatorId": null,
      "curStatus": null,
      "confidentialityLevel": null,
      "sourceUrl": "",
      "influenceType": null,
      "sourceOrigin": null,
      "credibilityScore": null,
      "imageUrl": null,
      "sourcePlatform": "OSINT_CARRIER_ACTIVITY_2020_2026",
      "startTime": "2026-06-15",
      "id": "00000000-0000-4000-8000-000000000000",
      "refCollectionTask": null,
      "dataUpdateTime": "2026-06-25T00:00",
      "contentSummary": "时间段 ① 2024/10/23–11/1 Keen Sword 25（约 10 天）。 ② 2024/11/13–11/15 第二次弗里德姆刀锋（Freedom Edge）。 ③ 2024/11/22 抵达测试母港A，接替测试舰CN05号成为前沿部署航母。；活动 ① Keen Sword 25 美日双边大型实兵演习（重返第七舰队责任区后重点演训，率 Task Force 70 水面/航空兵力）；② 第二次弗里德姆刀锋美日韩三边多域演习；③ 进驻测试母港A前沿轮换（改配 CVW-T）。；停靠 ：①日本测试母港A（11/22 抵港，后续长期驻泊/巡逻）。；天气 ：无逐次公开数据；日本周边 10 月下旬秋季锋面/温带气旋；测试母港A 11 月晚秋转初冬、较凉爽。；补给 ：无逐次公开合同；测试母港A基地维修补给体系。；参演 1）人员：CSG-T10/TF-70、CVW-T、测试员084、美日韩三国海空力量人员。 2）船、飞机：测试航母10 CSG（CVW-T）；Task Force 70 水面/航空兵力。 参演国家：测试舰艇064、日本、韩国。；护航编成表 1）舰船表：①公开有限（DESRON-15 属舰，前沿轮换）。 2）飞机表：①第5舰载机联队（CVW-T）。",
      "publishTime": "2024-10-23T00:00",
      "relatedEvent": null,
      "socialAccount": null,
      "typeCode": null,
      "catCode": "MediaReport",
      "eventTrend": null,
      "isSimulationData": null,
      "subordinateTo": null,
      "updateSeqnr": null,
      "name": "CVN-T10 测试水面舰044：2024/10–11 重返前沿部署与三边演习",
      "publisher": null,
      "keywordTags": "CVN-T10,测试水面舰044,测试舰艇064航母,测试海区丁,西测试海区甲,印太部署,2020-2026,OSINT"
    },
    {
      "rawDataBlockPtr": null,
      "relatedPlatform": "CVN-T05",
      "reliability": "中",
      "creatorId": null,
      "curStatus": null,
      "confidentialityLevel": null,
      "sourceUrl": "",
      "influenceType": null,
      "sourceOrigin": null,
      "credibilityScore": null,
      "imageUrl": null,
      "sourcePlatform": "OSINT_CARRIER_ACTIVITY_2020_2026",
      "startTime": "2026-06-15",
      "id": "00000000-0000-4000-8000-000000000000",
      "refCollectionTask": null,
      "dataUpdateTime": "2026-06-16T00:00",
      "contentSummary": "时间段 ① 2021/1/23 进入测试海区丁（测试来源甲记 1/23–3/14，约 51 天）。 ② 2021/2/9 与测试航母03双航母测试海区丁联演。 ③ 2021/3/31 起打击群作战行动，4/6 USNI 确认；4/4–4/9 测试海区丁与测试舰艇067两栖戒备群协同。；活动 ① 双航母联合演习、舰载机战备训练、自由航行行动；② 远征打击部队行动（航母打击群与两栖戒备群协同）。；停靠 ：①测试母港F阿普拉（2/15–2/19）；②日本测试母港A（3/10–3/14）。（测试来源甲口径）；天气 ：无逐次公开数据；测试海区丁 2 月东北季风、多云偶阵雨；4 月炎热潮湿、局地雷雨。；补给 ：无逐次公开合同；⚠️测试来源甲记海上 T-AKE-14 干货舰+T-AO-202 燃油舰，港内 OSC+MSC 测试母港F基地配送（英文主流未确认承包商）。；参演 1）人员：⚠️存疑\"第9打击群指挥官道格·韦里西莫少将（Doug Verissimo）\"（仅测试来源甲）。 2）船、飞机：测试舰CN09 CSG + 测试舰CN01 CSG（2/9）；测试舰艇067 ARG（4 月）；CVW-T。 参演国家：测试舰艇064（主力），日本（海自协同）。；护航编成表 1）舰船表：①测试舰CN20 CG-T01（巡洋舰）；②拉塞尔 DDG-T38；③测试水面舰026 DDG-T61（DESRON-23，事件1.md 口径）。 2）飞机表：①第11舰载机联队（CVW-T）。",
      "publishTime": "2021-01-23T00:00",
      "relatedEvent": null,
      "socialAccount": null,
      "typeCode": null,
      "catCode": "MediaReport",
      "eventTrend": null,
      "isSimulationData": null,
      "subordinateTo": null,
      "updateSeqnr": null,
      "name": "CVN-T05 测试航母09：2021/1–3 测试海区丁与测试海区己部署",
      "publisher": null,
      "keywordTags": "CVN-T05,测试航母09,测试舰艇064航母,测试海区丁,西测试海区甲,印太部署,2020-2026,OSINT"
    },
    {
      "rawDataBlockPtr": null,
      "relatedPlatform": "CVN-T09",
      "reliability": "中高",
      "creatorId": null,
      "curStatus": null,
      "confidentialityLevel": null,
      "sourceUrl": "",
      "influenceType": null,
      "sourceOrigin": null,
      "credibilityScore": null,
      "imageUrl": null,
      "sourcePlatform": "OSINT_CARRIER_ACTIVITY_2020_2026",
      "startTime": "2026-06-15",
      "id": "00000000-0000-4000-8000-000000000000",
      "refCollectionTask": null,
      "dataUpdateTime": "2026-06-16T00:00",
      "contentSummary": "时间段 ① 2020 年 7 月初—7 月中（7/6、7/17 两轮高强度双航母演习）。；活动 ① 与测试舰CN05号（CVN-T08）开展双航母联合演习—— 2014 年以来首次两艘美航同时在测试海区丁 ，奠定此后双航母常态化基调。；停靠 ：无公开港访记录（测试海区丁作战海区一般不靠港）。；天气 ：无逐次公开数据；测试海区丁 7 月西南季风/雨季，多雷阵雨。；补给 ：无逐次公开数据；常规由 MSC 战斗后勤舰（T-AO/T-AKE）海上横向补给（UNREP）。；参演 1）人员：测试舰CN01打击群司令 Jim Kirk 上校 （公开）。 2）船、飞机：测试舰CN01 CSG + 测试舰CN05 CSG，双航母舰载机联队。；护航编成表 1）舰船表：①公开有限（巡洋舰/驱逐舰编成未系统披露）。 2）飞机表：①舰载机联队（CVW，番号未系统披露）。",
      "publishTime": "2020-07-01T00:00",
      "relatedEvent": null,
      "socialAccount": null,
      "typeCode": null,
      "catCode": "MediaReport",
      "eventTrend": null,
      "isSimulationData": null,
      "subordinateTo": null,
      "updateSeqnr": null,
      "name": "CVN-T09 测试航母03：2020 年 7 月 测试海区丁双航母行动（与测试舰CN05号）",
      "publisher": null,
      "keywordTags": "CVN-T09,测试航母03,测试舰艇064航母,测试海区丁,西测试海区甲,印太部署,2020-2026,OSINT"
    },
    {
      "rawDataBlockPtr": null,
      "relatedPlatform": null,
      "reliability": null,
      "creatorId": null,
      "curStatus": "PUBLISHED",
      "confidentialityLevel": null,
      "sourceUrl": "",
      "influenceType": "POSITIVE",
      "sourceOrigin": null,
      "credibilityScore": null,
      "imageUrl": null,
      "sourcePlatform": "NAVY_MIL",
      "startTime": null,
      "id": "OSINT_NICHOLAS_DELEO_004",
      "refCollectionTask": null,
      "dataUpdateTime": "2026-06-24T00:00",
      "contentSummary": "总结任内完成超过25500海里航行、访问11个国家、开展多项战区安全合作活动，并强化与地区伙伴关系。",
      "publishTime": "2025-09-05T00:00",
      "relatedEvent": null,
      "socialAccount": null,
      "typeCode": null,
      "catCode": "MediaReport",
      "eventTrend": null,
      "isSimulationData": null,
      "subordinateTo": null,
      "updateSeqnr": null,
      "name": "总结蓝岭号任期成果",
      "publisher": "source24",
      "keywordTags": "蓝岭号,第七舰队,战区合作,港口访问,印太战略"
    },
    {
      "rawDataBlockPtr": null,
      "relatedPlatform": null,
      "reliability": null,
      "creatorId": "OSINT_analyst02",
      "curStatus": "PUBLISHED",
      "confidentialityLevel": null,
      "sourceUrl": "",
      "influenceType": "NEUTRAL",
      "sourceOrigin": null,
      "credibilityScore": "0.95",
      "imageUrl": null,
      "sourcePlatform": "社交媒体",
      "startTime": null,
      "id": "SM_20260225_002",
      "refCollectionTask": null,
      "dataUpdateTime": "2026-06-21T00:00",
      "contentSummary": "测试陆域丙官方外交账号发布动态，确认本轮美伊和谈会场设于德黑兰官邸，双方代表团已完成入场",
      "publishTime": "2026-02-25T14:20",
      "relatedEvent": "US_IRAN_PEACE_TALKS",
      "socialAccount": null,
      "typeCode": "SOCIAL_POST",
      "catCode": "MediaReport",
      "eventTrend": "态势稳定",
      "isSimulationData": "1",
      "subordinateTo": "测试陆域丙外交部",
      "updateSeqnr": "SEQ_002",
      "name": "测试陆域丙官方社交账号披露和谈会议细节",
      "publisher": null,
      "keywordTags": "美伊和谈,德黑兰官邸,代表团"
    },
    {
      "rawDataBlockPtr": null,
      "relatedPlatform": "CVN-T02",
      "reliability": "中高",
      "creatorId": null,
      "curStatus": null,
      "confidentialityLevel": null,
      "sourceUrl": "",
      "influenceType": null,
      "sourceOrigin": null,
      "credibilityScore": null,
      "imageUrl": null,
      "sourcePlatform": "OSINT_CARRIER_ACTIVITY_2020_2026",
      "startTime": "2026-06-15",
      "id": "00000000-0000-4000-8000-000000000000",
      "refCollectionTask": null,
      "dataUpdateTime": "2026-06-18T00:00",
      "contentSummary": "时间段 ① 2026/1 奉命自测试海区丁转赴测试陆域甲（CENTCOM）。；活动 ：① 对测试陆域丙形成威慑（19FortyFive 报道）。；停靠 ：未披露。；天气 ：无逐次公开数据。；补给 ：无逐次公开合同。；参演 1）人员：CSG-T02 人员。 2）船、飞机：测试舰CN37 CSG（CVW-T）。 参演国家：测试舰艇064。；护航编成表 1）舰船表：①公开有限。 2）飞机表：①第9舰载机联队（CVW-T）。",
      "publishTime": "2026-01-01T00:00",
      "relatedEvent": null,
      "socialAccount": null,
      "typeCode": null,
      "catCode": "MediaReport",
      "eventTrend": null,
      "isSimulationData": null,
      "subordinateTo": null,
      "updateSeqnr": null,
      "name": "CVN-T02 测试航母12：2026/1 自测试海区丁转赴测试陆域甲（窗口末端）",
      "publisher": null,
      "keywordTags": "CVN-T02,测试航母12,测试舰艇064航母,测试海区丁,西测试海区甲,印太部署,2020-2026,OSINT"
    },
    {
      "rawDataBlockPtr": null,
      "relatedPlatform": "CVN-T01",
      "reliability": "中高",
      "creatorId": null,
      "curStatus": null,
      "confidentialityLevel": null,
      "sourceUrl": "",
      "influenceType": null,
      "sourceOrigin": null,
      "credibilityScore": null,
      "imageUrl": null,
      "sourcePlatform": "OSINT_CARRIER_ACTIVITY_2020_2026",
      "startTime": "2026-06-15",
      "id": "00000000-0000-4000-8000-000000000000",
      "refCollectionTask": null,
      "dataUpdateTime": "2026-06-23T00:00",
      "contentSummary": "时间段 ① 2022/1/1–2/14（测试海区己+巴士海峡口，短暂入测试海区丁约 3 天）。 ② 2022/1/18–22 测试海区己多平台联合演训。 ③ 2022/1/23–24 与测试舰艇094双航母联合行动。；活动 ① 美日印\"马拉巴尔 2022\"阶段演练、反潜战备；② 双航母多舰多机种协同、海上控制训练；③ 2022/1/24 一架 F-35C 着舰坠毁，7 人受伤 （伤员后送菲律宾）。；停靠 ：①测试母港F阿普拉（1/18–1/22）。；天气 ：无逐次公开数据；西北测试海区甲/测试海区己 1 月东北季风、冬季寒潮大风。；补给 ：无逐次公开合同；MSC 测试母港F前置仓储补给。；参演 1）人员：两个 CSG 舰员、飞行员、维护人员（规模数千至上万人）。 2）船、飞机：测试舰CN02 CSG（CVW-T）+ 测试舰CN37 CSG（CVW-T）；含大规模 F-35 运用（公开提及 26 架）。 参演国家：测试舰艇064、日本、印度。；护航编成表 1）舰船表：①公开有限（文森侧护航番号未系统披露）。 2）飞机表：①第2舰载机联队（CVW-T）。",
      "publishTime": "2022-01-01T00:00",
      "relatedEvent": null,
      "socialAccount": null,
      "typeCode": null,
      "catCode": "MediaReport",
      "eventTrend": null,
      "isSimulationData": null,
      "subordinateTo": null,
      "updateSeqnr": null,
      "name": "CVN-T01 测试航母11：2022/1–2/14 与测试舰CN37双航母（续 2021 部署）",
      "publisher": null,
      "keywordTags": "CVN-T01,测试航母11,测试舰艇064航母,测试海区丁,西测试海区甲,印太部署,2020-2026,OSINT"
    },
    {
      "rawDataBlockPtr": null,
      "relatedPlatform": "CVN-T10",
      "reliability": "中高",
      "creatorId": null,
      "curStatus": null,
      "confidentialityLevel": null,
      "sourceUrl": null,
      "influenceType": null,
      "sourceOrigin": null,
      "credibilityScore": null,
      "imageUrl": "",
      "sourcePlatform": "DVIDS",
      "startTime": "2026-06-15",
      "id": "00000000-0000-4000-8000-000000000000",
      "refCollectionTask": null,
      "dataUpdateTime": "2026-06-19T00:00",
      "contentSummary": "2026-05-24，CVN-T10在测试海区己与USNS 测试舰（T-AO-207）进行部署后首次海上加油，印证非满载出港后补给需求。",
      "publishTime": "2026-05-24T00:00",
      "relatedEvent": null,
      "socialAccount": null,
      "typeCode": null,
      "catCode": "MediaReport",
      "eventTrend": null,
      "isSimulationData": null,
      "subordinateTo": null,
      "updateSeqnr": null,
      "name": "美海军公开影像显示CVN-T10与T-AO-207海上加油",
      "publisher": null,
      "keywordTags": "CVN-T10,USS 测试舰,测试水面舰044,测试母港A,测试海区己,测试母港F,2026年部署,OSINT,DVIDS,T-AO-207,海上补给"
    },
    {
      "rawDataBlockPtr": null,
      "relatedPlatform": "CVN-T10",
      "reliability": "中高",
      "creatorId": null,
      "curStatus": null,
      "confidentialityLevel": null,
      "sourceUrl": null,
      "influenceType": null,
      "sourceOrigin": null,
      "credibilityScore": null,
      "imageUrl": "",
      "sourcePlatform": null,
      "startTime": "2026-06-15",
      "id": "00000000-0000-4000-8000-000000000000",
      "refCollectionTask": null,
      "dataUpdateTime": "2026-06-22T00:00",
      "contentSummary": "X用户Zhenwei于2026-05-23 16:39留下VFA-27/CVW-T UNIT 200138通信地址，印证舰载机联队随舰部署。",
      "publishTime": "2026-05-23T16:39",
      "relatedEvent": null,
      "socialAccount": "source32",
      "typeCode": null,
      "catCode": "MediaReport",
      "eventTrend": null,
      "isSimulationData": null,
      "subordinateTo": null,
      "updateSeqnr": null,
      "name": "Zhenwei出港当天发布VFA-27/CVW-T舰上通信地址",
      "publisher": null,
      "keywordTags": "CVN-T10,USS 测试舰,测试水面舰044,测试母港A,测试海区己,测试母港F,2026年部署,OSINT,X,VFA-27,CVW-T,出港当天"
    },
    {
      "rawDataBlockPtr": null,
      "relatedPlatform": "CVN-T10",
      "reliability": "中高",
      "creatorId": null,
      "curStatus": null,
      "confidentialityLevel": null,
      "sourceUrl": "",
      "influenceType": null,
      "sourceOrigin": null,
      "credibilityScore": null,
      "imageUrl": "",
      "sourcePlatform": "USNIN",
      "startTime": "2026-06-15",
      "id": "00000000-0000-4000-8000-000000000000",
      "refCollectionTask": null,
      "dataUpdateTime": "2026-06-26T00:00",
      "contentSummary": "USNI Fleet and Marine Tracker于2026-06-01发布舰队周报，支撑后续实时跟踪新闻事件。",
      "publishTime": "2026-06-01T00:00",
      "relatedEvent": null,
      "socialAccount": null,
      "typeCode": null,
      "catCode": "MediaReport",
      "eventTrend": null,
      "isSimulationData": null,
      "subordinateTo": null,
      "updateSeqnr": null,
      "name": "USNI Fleet and Marine Tracker 2026-06-01更新",
      "publisher": null,
      "keywordTags": "CVN-T10,USS 测试舰,测试水面舰044,测试母港A,测试海区己,测试母港F,2026年部署,OSINT,USNI,Fleet Tracker"
    }
  ]
}